{"timeframe":  "24h",
"token":  "kaspa",
"exchange":  "cex",
"resolution":  "1m",
"count":  82,
"data":  [{"token":  "Kaspa",
    "exchange":  "cex",
    "symbol":  "KAS/USDT",
    "last":  0.04299,
    "bid":  0.042930000000000003,
    "ask":  0.04299,
    "open":  0.043970000000000002,
    "close":  0.04299,
    "high":  0.04301,
    "low":  0.04301,
    "average":  0.043479999999999998,
    "vwap":  0.04301,
    "previousClose":  null,
    "volume":  null,
    "baseVolume":  480.600000000000022737,
    "quoteVolume":  20.670605999999999369,
    "bidVolume":  null,
    "askVolume":  null,
    "change":  -0.00098,
    "percentage":  -2.25,
    "timestamp":  1767225600057,
    "datetime":  "2026-01-01T00:00:00.057684",
    "exchange_timestamp":  "2026-01-01T00:00:00.057686",
    "data_source":  "official_exchange_api",
    "exchange_id":  "cex"},
  {"token":  "Kaspa",
    "exchange":  "cex",
    "symbol":  "KAS/USDT",
    "last":  0.042979999999999997,
    "bid":  0.042930000000000003,
    "ask":  0.042979999999999997,
    "open":  0.043979999999999998,
    "close":  0.042979999999999997,
    "high":  0.04301,
    "low":  0.04301,
    "average":  0.043479999999999998,
    "vwap":  0.04301,
    "previousClose":  null,
    "volume":  null,
    "baseVolume":  480.600000000000022737,
    "quoteVolume":  20.670605999999999369,
    "bidVolume":  null,
    "askVolume":  null,
    "change":  -0.001,
    "percentage":  -2.270000000000000018,
    "timestamp":  1767225635491,
    "datetime":  "2026-01-01T00:00:35.491367",
    "exchange_timestamp":  "2026-01-01T00:00:35.491370",
    "data_source":  "official_exchange_api",
    "exchange_id":  "cex"},
  {"token":  "Kaspa",
    "exchange":  "cex",
    "symbol":  "KAS/USDT",
    "last":  0.043069999999999997,
    "bid":  0.043020000000000003,
    "ask":  0.043069999999999997,
    "open":  0.043959999999999999,
    "close":  0.043069999999999997,
    "high":  0.04301,
    "low":  0.04301,
    "average":  0.04351,
    "vwap":  0.04301,
    "previousClose":  null,
    "volume":  null,
    "baseVolume":  480.600000000000022737,
    "quoteVolume":  20.670605999999999369,
    "bidVolume":  null,
    "askVolume":  null,
    "change":  -0.00089,
    "percentage":  -2.020000000000000018,
    "timestamp":  1767225711634,
    "datetime":  "2026-01-01T00:01:51.634910",
    "exchange_timestamp":  "2026-01-01T00:01:51.634913",
    "data_source":  "official_exchange_api",
    "exchange_id":  "cex"},
  {"token":  "Kaspa",
    "exchange":  "cex",
    "symbol":  "KAS/USDT",
    "last":  0.04308,
    "bid":  0.043020000000000003,
    "ask":  0.04308,
    "open":  0.043950000000000003,
    "close":  0.04308,
    "high":  0.04301,
    "low":  0.04301,
    "average":  0.04351,
    "vwap":  0.04301,
    "previousClose":  null,
    "volume":  null,
    "baseVolume":  480.600000000000022737,
    "quoteVolume":  20.670605999999999369,
    "bidVolume":  null,
    "askVolume":  null,
    "change":  -0.00087,
    "percentage":  -2,
    "timestamp":  1767225734194,
    "datetime":  "2026-01-01T00:02:14.194186",
    "exchange_timestamp":  "2026-01-01T00:02:14.194188",
    "data_source":  "official_exchange_api",
    "exchange_id":  "cex"},
  {"token":  "Kaspa",
    "exchange":  "cex",
    "symbol":  "KAS/USDT",
    "last":  0.043110000000000002,
    "bid":  0.043049999999999998,
    "ask":  0.043110000000000002,
    "open":  0.043950000000000003,
    "close":  0.043110000000000002,
    "high":  0.04301,
    "low":  0.04301,
    "average":  0.043529999999999999,
    "vwap":  0.04301,
    "previousClose":  null,
    "volume":  null,
    "baseVolume":  480.600000000000022737,
    "quoteVolume":  20.670605999999999369,
    "bidVolume":  null,
    "askVolume":  null,
    "change":  -0.00084,
    "percentage":  -1.90999999999999992,
    "timestamp":  1767225818921,
    "datetime":  "2026-01-01T00:03:38.921973",
    "exchange_timestamp":  "2026-01-01T00:03:38.921976",
    "data_source":  "official_exchange_api",
    "exchange_id":  "cex"},
  {"token":  "Kaspa",
    "exchange":  "cex",
    "symbol":  "KAS/USDT",
    "last":  0.043099999999999999,
    "bid":  0.043049999999999998,
    "ask":  0.043099999999999999,
    "open":  0.043950000000000003,
    "close":  0.043099999999999999,
    "high":  0.04301,
    "low":  0.04301,
    "average":  0.043520000000000003,
    "vwap":  0.04301,
    "previousClose":  null,
    "volume":  null,
    "baseVolume":  480.600000000000022737,
    "quoteVolume":  20.670605999999999369,
    "bidVolume":  null,
    "askVolume":  null,
    "change":  -0.00085,
    "percentage":  -1.929999999999999938,
    "timestamp":  1767225864804,
    "datetime":  "2026-01-01T00:04:24.804338",
    "exchange_timestamp":  "2026-01-01T00:04:24.804341",
    "data_source":  "official_exchange_api",
    "exchange_id":  "cex"},
  {"token":  "Kaspa",
    "exchange":  "cex",
    "symbol":  "KAS/USDT",
    "last":  0.043119999999999999,
    "bid":  0.043069999999999997,
    "ask":  0.043119999999999999,
    "open":  0.043950000000000003,
    "close":  0.043119999999999999,
    "high":  0.04301,
    "low":  0.04301,
    "average":  0.043529999999999999,
    "vwap":  0.04301,
    "previousClose":  null,
    "volume":  null,
    "baseVolume":  480.600000000000022737,
    "quoteVolume":  20.670605999999999369,
    "bidVolume":  null,
    "askVolume":  null,
    "change":  -0.00083,
    "percentage":  -1.879999999999999893,
    "timestamp":  1767225948690,
    "datetime":  "2026-01-01T00:05:48.690411",
    "exchange_timestamp":  "2026-01-01T00:05:48.690415",
    "data_source":  "official_exchange_api",
    "exchange_id":  "cex"},
  {"token":  "Kaspa",
    "exchange":  "cex",
    "symbol":  "KAS/USDT",
    "last":  0.043099999999999999,
    "bid":  0.043040000000000002,
    "ask":  0.043099999999999999,
    "open":  0.043900000000000002,
    "close":  0.043099999999999999,
    "high":  0.04301,
    "low":  0.04301,
    "average":  0.043499999999999997,
    "vwap":  0.04301,
    "previousClose":  null,
    "volume":  null,
    "baseVolume":  480.600000000000022737,
    "quoteVolume":  20.670605999999999369,
    "bidVolume":  null,
    "askVolume":  null,
    "change":  -0.0008,
    "percentage":  -1.84000000000000008,
    "timestamp":  1767226005121,
    "datetime":  "2026-01-01T00:06:45.121594",
    "exchange_timestamp":  "2026-01-01T00:06:45.121598",
    "data_source":  "official_exchange_api",
    "exchange_id":  "cex"},
  {"token":  "Kaspa",
    "exchange":  "cex",
    "symbol":  "KAS/USDT",
    "last":  0.043069999999999997,
    "bid":  0.04301,
    "ask":  0.043069999999999997,
    "open":  0.043909999999999998,
    "close":  0.043069999999999997,
    "high":  0.04301,
    "low":  0.04301,
    "average":  0.043490000000000001,
    "vwap":  0.04301,
    "previousClose":  null,
    "volume":  null,
    "baseVolume":  480.600000000000022737,
    "quoteVolume":  20.670605999999999369,
    "bidVolume":  null,
    "askVolume":  null,
    "change":  -0.00084,
    "percentage":  -1.90999999999999992,
    "timestamp":  1767226037856,
    "datetime":  "2026-01-01T00:07:17.856541",
    "exchange_timestamp":  "2026-01-01T00:07:17.856543",
    "data_source":  "official_exchange_api",
    "exchange_id":  "cex"},
  {"token":  "Kaspa",
    "exchange":  "cex",
    "symbol":  "KAS/USDT",
    "last":  0.043119999999999999,
    "bid":  0.043060000000000001,
    "ask":  0.043119999999999999,
    "open":  0.043830000000000001,
    "close":  0.043119999999999999,
    "high":  0.04301,
    "low":  0.04301,
    "average":  0.043470000000000002,
    "vwap":  0.04301,
    "previousClose":  null,
    "volume":  null,
    "baseVolume":  480.600000000000022737,
    "quoteVolume":  20.670605999999999369,
    "bidVolume":  null,
    "askVolume":  null,
    "change":  -0.00071,
    "percentage":  -1.639999999999999902,
    "timestamp":  1767226105022,
    "datetime":  "2026-01-01T00:08:25.022689",
    "exchange_timestamp":  "2026-01-01T00:08:25.022691",
    "data_source":  "official_exchange_api",
    "exchange_id":  "cex"},
  {"token":  "Kaspa",
    "exchange":  "cex",
    "symbol":  "KAS/USDT",
    "last":  0.043119999999999999,
    "bid":  0.043060000000000001,
    "ask":  0.043119999999999999,
    "open":  0.043830000000000001,
    "close":  0.043119999999999999,
    "high":  0.04301,
    "low":  0.04301,
    "average":  0.043470000000000002,
    "vwap":  0.04301,
    "previousClose":  null,
    "volume":  null,
    "baseVolume":  480.600000000000022737,
    "quoteVolume":  20.670605999999999369,
    "bidVolume":  null,
    "askVolume":  null,
    "change":  -0.00071,
    "percentage":  -1.639999999999999902,
    "timestamp":  1767226105426,
    "datetime":  "2026-01-01T00:08:25.426761",
    "exchange_timestamp":  "2026-01-01T00:08:25.426764",
    "data_source":  "official_exchange_api",
    "exchange_id":  "cex"},
  {"token":  "Kaspa",
    "exchange":  "cex",
    "symbol":  "KAS/USDT",
    "last":  0.043119999999999999,
    "bid":  0.043049999999999998,
    "ask":  0.043119999999999999,
    "open":  0.043830000000000001,
    "close":  0.043119999999999999,
    "high":  0.04301,
    "low":  0.04301,
    "average":  0.043470000000000002,
    "vwap":  0.04301,
    "previousClose":  null,
    "volume":  null,
    "baseVolume":  480.600000000000022737,
    "quoteVolume":  20.670605999999999369,
    "bidVolume":  null,
    "askVolume":  null,
    "change":  -0.00071,
    "percentage":  -1.639999999999999902,
    "timestamp":  1767226162611,
    "datetime":  "2026-01-01T00:09:22.611960",
    "exchange_timestamp":  "2026-01-01T00:09:22.611963",
    "data_source":  "official_exchange_api",
    "exchange_id":  "cex"},
  {"token":  "Kaspa",
    "exchange":  "cex",
    "symbol":  "KAS/USDT",
    "last":  0.043110000000000002,
    "bid":  0.043049999999999998,
    "ask":  0.043110000000000002,
    "open":  0.043830000000000001,
    "close":  0.043110000000000002,
    "high":  0.04301,
    "low":  0.04301,
    "average":  0.043470000000000002,
    "vwap":  0.04301,
    "previousClose":  null,
    "volume":  null,
    "baseVolume":  480.600000000000022737,
    "quoteVolume":  20.670605999999999369,
    "bidVolume":  null,
    "askVolume":  null,
    "change":  -0.00072,
    "percentage":  -1.65999999999999992,
    "timestamp":  1767226207977,
    "datetime":  "2026-01-01T00:10:07.977763",
    "exchange_timestamp":  "2026-01-01T00:10:07.977765",
    "data_source":  "official_exchange_api",
    "exchange_id":  "cex"},
  {"token":  "Kaspa",
    "exchange":  "cex",
    "symbol":  "KAS/USDT",
    "last":  0.043110000000000002,
    "bid":  0.043060000000000001,
    "ask":  0.043110000000000002,
    "open":  0.043839999999999997,
    "close":  0.043110000000000002,
    "high":  0.04301,
    "low":  0.04301,
    "average":  0.043470000000000002,
    "vwap":  0.04301,
    "previousClose":  null,
    "volume":  null,
    "baseVolume":  480.600000000000022737,
    "quoteVolume":  20.670605999999999369,
    "bidVolume":  null,
    "askVolume":  null,
    "change":  -0.00073,
    "percentage":  -1.679999999999999938,
    "timestamp":  1767226241687,
    "datetime":  "2026-01-01T00:10:41.687336",
    "exchange_timestamp":  "2026-01-01T00:10:41.687337",
    "data_source":  "official_exchange_api",
    "exchange_id":  "cex"},
  {"token":  "Kaspa",
    "exchange":  "cex",
    "symbol":  "KAS/USDT",
    "last":  0.043119999999999999,
    "bid":  0.043060000000000001,
    "ask":  0.043119999999999999,
    "open":  0.04385,
    "close":  0.043119999999999999,
    "high":  0.04301,
    "low":  0.04301,
    "average":  0.043479999999999998,
    "vwap":  0.04301,
    "previousClose":  null,
    "volume":  null,
    "baseVolume":  480.600000000000022737,
    "quoteVolume":  20.670605999999999369,
    "bidVolume":  null,
    "askVolume":  null,
    "change":  -0.00073,
    "percentage":  -1.65999999999999992,
    "timestamp":  1767226294598,
    "datetime":  "2026-01-01T00:11:34.598191",
    "exchange_timestamp":  "2026-01-01T00:11:34.598193",
    "data_source":  "official_exchange_api",
    "exchange_id":  "cex"},
  {"token":  "Kaspa",
    "exchange":  "cex",
    "symbol":  "KAS/USDT",
    "last":  0.043119999999999999,
    "bid":  0.043060000000000001,
    "ask":  0.043119999999999999,
    "open":  0.04385,
    "close":  0.043119999999999999,
    "high":  0.04301,
    "low":  0.04301,
    "average":  0.043479999999999998,
    "vwap":  0.04301,
    "previousClose":  null,
    "volume":  null,
    "baseVolume":  480.600000000000022737,
    "quoteVolume":  20.670605999999999369,
    "bidVolume":  null,
    "askVolume":  null,
    "change":  -0.00073,
    "percentage":  -1.65999999999999992,
    "timestamp":  1767226301565,
    "datetime":  "2026-01-01T00:11:41.565434",
    "exchange_timestamp":  "2026-01-01T00:11:41.565437",
    "data_source":  "official_exchange_api",
    "exchange_id":  "cex"},
  {"token":  "Kaspa",
    "exchange":  "cex",
    "symbol":  "KAS/USDT",
    "last":  0.043119999999999999,
    "bid":  0.043060000000000001,
    "ask":  0.043119999999999999,
    "open":  0.043830000000000001,
    "close":  0.043119999999999999,
    "high":  0.04301,
    "low":  0.04301,
    "average":  0.043470000000000002,
    "vwap":  0.04301,
    "previousClose":  null,
    "volume":  null,
    "baseVolume":  480.600000000000022737,
    "quoteVolume":  20.670605999999999369,
    "bidVolume":  null,
    "askVolume":  null,
    "change":  -0.00071,
    "percentage":  -1.610000000000000098,
    "timestamp":  1767226361901,
    "datetime":  "2026-01-01T00:12:41.901359",
    "exchange_timestamp":  "2026-01-01T00:12:41.901361",
    "data_source":  "official_exchange_api",
    "exchange_id":  "cex"},
  {"token":  "Kaspa",
    "exchange":  "cex",
    "symbol":  "KAS/USDT",
    "last":  0.043119999999999999,
    "bid":  0.043060000000000001,
    "ask":  0.043119999999999999,
    "open":  0.043830000000000001,
    "close":  0.043119999999999999,
    "high":  0.04301,
    "low":  0.04301,
    "average":  0.043470000000000002,
    "vwap":  0.04301,
    "previousClose":  null,
    "volume":  null,
    "baseVolume":  480.600000000000022737,
    "quoteVolume":  20.670605999999999369,
    "bidVolume":  null,
    "askVolume":  null,
    "change":  -0.00071,
    "percentage":  -1.610000000000000098,
    "timestamp":  1767226380989,
    "datetime":  "2026-01-01T00:13:00.989284",
    "exchange_timestamp":  "2026-01-01T00:13:00.989286",
    "data_source":  "official_exchange_api",
    "exchange_id":  "cex"},
  {"token":  "Kaspa",
    "exchange":  "cex",
    "symbol":  "KAS/USDT",
    "last":  0.043099999999999999,
    "bid":  0.043040000000000002,
    "ask":  0.043099999999999999,
    "open":  0.043830000000000001,
    "close":  0.043099999999999999,
    "high":  0.04301,
    "low":  0.04301,
    "average":  0.043459999999999999,
    "vwap":  0.04301,
    "previousClose":  null,
    "volume":  null,
    "baseVolume":  480.600000000000022737,
    "quoteVolume":  20.670605999999999369,
    "bidVolume":  null,
    "askVolume":  null,
    "change":  -0.00073,
    "percentage":  -1.65999999999999992,
    "timestamp":  1767226428112,
    "datetime":  "2026-01-01T00:13:48.112405",
    "exchange_timestamp":  "2026-01-01T00:13:48.112407",
    "data_source":  "official_exchange_api",
    "exchange_id":  "cex"},
  {"token":  "Kaspa",
    "exchange":  "cex",
    "symbol":  "KAS/USDT",
    "last":  0.043099999999999999,
    "bid":  0.043049999999999998,
    "ask":  0.043099999999999999,
    "open":  0.043830000000000001,
    "close":  0.043099999999999999,
    "high":  0.04301,
    "low":  0.04301,
    "average":  0.043459999999999999,
    "vwap":  0.04301,
    "previousClose":  null,
    "volume":  null,
    "baseVolume":  480.600000000000022737,
    "quoteVolume":  20.670605999999999369,
    "bidVolume":  null,
    "askVolume":  null,
    "change":  -0.00073,
    "percentage":  -1.65999999999999992,
    "timestamp":  1767226473541,
    "datetime":  "2026-01-01T00:14:33.541935",
    "exchange_timestamp":  "2026-01-01T00:14:33.541942",
    "data_source":  "official_exchange_api",
    "exchange_id":  "cex"},
  {"token":  "Kaspa",
    "exchange":  "cex",
    "symbol":  "KAS/USDT",
    "last":  0.043099999999999999,
    "bid":  0.043049999999999998,
    "ask":  0.043099999999999999,
    "open":  0.043830000000000001,
    "close":  0.043099999999999999,
    "high":  0.04301,
    "low":  0.04301,
    "average":  0.043459999999999999,
    "vwap":  0.04301,
    "previousClose":  null,
    "volume":  null,
    "baseVolume":  480.600000000000022737,
    "quoteVolume":  20.670605999999999369,
    "bidVolume":  null,
    "askVolume":  null,
    "change":  -0.00073,
    "percentage":  -1.65999999999999992,
    "timestamp":  1767226489120,
    "datetime":  "2026-01-01T00:14:49.120665",
    "exchange_timestamp":  "2026-01-01T00:14:49.120667",
    "data_source":  "official_exchange_api",
    "exchange_id":  "cex"},
  {"token":  "Kaspa",
    "exchange":  "cex",
    "symbol":  "KAS/USDT",
    "last":  0.043130000000000002,
    "bid":  0.043069999999999997,
    "ask":  0.043130000000000002,
    "open":  0.043819999999999998,
    "close":  0.043130000000000002,
    "high":  0.04301,
    "low":  0.04301,
    "average":  0.043470000000000002,
    "vwap":  0.04301,
    "previousClose":  null,
    "volume":  null,
    "baseVolume":  480.600000000000022737,
    "quoteVolume":  20.670605999999999369,
    "bidVolume":  null,
    "askVolume":  null,
    "change":  -0.00069,
    "percentage":  -1.59000000000000008,
    "timestamp":  1767226561468,
    "datetime":  "2026-01-01T00:16:01.468059",
    "exchange_timestamp":  "2026-01-01T00:16:01.468061",
    "data_source":  "official_exchange_api",
    "exchange_id":  "cex"},
  {"token":  "Kaspa",
    "exchange":  "cex",
    "symbol":  "KAS/USDT",
    "last":  0.043189999999999999,
    "bid":  0.043119999999999999,
    "ask":  0.043189999999999999,
    "open":  0.043830000000000001,
    "close":  0.043189999999999999,
    "high":  0.04301,
    "low":  0.04301,
    "average":  0.04351,
    "vwap":  0.04301,
    "previousClose":  null,
    "volume":  null,
    "baseVolume":  480.600000000000022737,
    "quoteVolume":  20.670605999999999369,
    "bidVolume":  null,
    "askVolume":  null,
    "change":  -0.00064,
    "percentage":  -1.459999999999999964,
    "timestamp":  1767226572725,
    "datetime":  "2026-01-01T00:16:12.725398",
    "exchange_timestamp":  "2026-01-01T00:16:12.725400",
    "data_source":  "official_exchange_api",
    "exchange_id":  "cex"},
  {"token":  "Kaspa",
    "exchange":  "cex",
    "symbol":  "KAS/USDT",
    "last":  0.043139999999999998,
    "bid":  0.043069999999999997,
    "ask":  0.043139999999999998,
    "open":  0.043830000000000001,
    "close":  0.043139999999999998,
    "high":  0.04301,
    "low":  0.04301,
    "average":  0.043479999999999998,
    "vwap":  0.04301,
    "previousClose":  null,
    "volume":  null,
    "baseVolume":  480.600000000000022737,
    "quoteVolume":  20.670605999999999369,
    "bidVolume":  null,
    "askVolume":  null,
    "change":  -0.00069,
    "percentage":  -1.570000000000000062,
    "timestamp":  1767226631523,
    "datetime":  "2026-01-01T00:17:11.523322",
    "exchange_timestamp":  "2026-01-01T00:17:11.523324",
    "data_source":  "official_exchange_api",
    "exchange_id":  "cex"},
  {"token":  "Kaspa",
    "exchange":  "cex",
    "symbol":  "KAS/USDT",
    "last":  0.043139999999999998,
    "bid":  0.04308,
    "ask":  0.043139999999999998,
    "open":  0.043819999999999998,
    "close":  0.043139999999999998,
    "high":  0.04301,
    "low":  0.04301,
    "average":  0.043479999999999998,
    "vwap":  0.04301,
    "previousClose":  null,
    "volume":  null,
    "baseVolume":  480.600000000000022737,
    "quoteVolume":  20.670605999999999369,
    "bidVolume":  null,
    "askVolume":  null,
    "change":  -0.00068,
    "percentage":  -1.550000000000000044,
    "timestamp":  1767226680021,
    "datetime":  "2026-01-01T00:18:00.021484",
    "exchange_timestamp":  "2026-01-01T00:18:00.021486",
    "data_source":  "official_exchange_api",
    "exchange_id":  "cex"},
  {"token":  "Kaspa",
    "exchange":  "cex",
    "symbol":  "KAS/USDT",
    "last":  0.043150000000000001,
    "bid":  0.043090000000000003,
    "ask":  0.043150000000000001,
    "open":  0.043810000000000002,
    "close":  0.043150000000000001,
    "high":  0.04301,
    "low":  0.04301,
    "average":  0.043479999999999998,
    "vwap":  0.04301,
    "previousClose":  null,
    "volume":  null,
    "baseVolume":  480.600000000000022737,
    "quoteVolume":  20.670605999999999369,
    "bidVolume":  null,
    "askVolume":  null,
    "change":  -0.00066,
    "percentage":  -1.520000000000000018,
    "timestamp":  1767226712941,
    "datetime":  "2026-01-01T00:18:32.941064",
    "exchange_timestamp":  "2026-01-01T00:18:32.941066",
    "data_source":  "official_exchange_api",
    "exchange_id":  "cex"},
  {"token":  "Kaspa",
    "exchange":  "cex",
    "symbol":  "KAS/USDT",
    "last":  0.043150000000000001,
    "bid":  0.043090000000000003,
    "ask":  0.043150000000000001,
    "open":  0.043790000000000003,
    "close":  0.043150000000000001,
    "high":  0.04301,
    "low":  0.04301,
    "average":  0.043470000000000002,
    "vwap":  0.04301,
    "previousClose":  null,
    "volume":  null,
    "baseVolume":  480.600000000000022737,
    "quoteVolume":  20.670605999999999369,
    "bidVolume":  null,
    "askVolume":  null,
    "change":  -0.00064,
    "percentage":  -1.479999999999999982,
    "timestamp":  1767226782200,
    "datetime":  "2026-01-01T00:19:42.200960",
    "exchange_timestamp":  "2026-01-01T00:19:42.200962",
    "data_source":  "official_exchange_api",
    "exchange_id":  "cex"},
  {"token":  "Kaspa",
    "exchange":  "cex",
    "symbol":  "KAS/USDT",
    "last":  0.043150000000000001,
    "bid":  0.043090000000000003,
    "ask":  0.043150000000000001,
    "open":  0.043790000000000003,
    "close":  0.043150000000000001,
    "high":  0.04301,
    "low":  0.04301,
    "average":  0.043470000000000002,
    "vwap":  0.04301,
    "previousClose":  null,
    "volume":  null,
    "baseVolume":  480.600000000000022737,
    "quoteVolume":  20.670605999999999369,
    "bidVolume":  null,
    "askVolume":  null,
    "change":  -0.00064,
    "percentage":  -1.479999999999999982,
    "timestamp":  1767226787411,
    "datetime":  "2026-01-01T00:19:47.411614",
    "exchange_timestamp":  "2026-01-01T00:19:47.411616",
    "data_source":  "official_exchange_api",
    "exchange_id":  "cex"},
  {"token":  "Kaspa",
    "exchange":  "cex",
    "symbol":  "KAS/USDT",
    "last":  0.043130000000000002,
    "bid":  0.043069999999999997,
    "ask":  0.043130000000000002,
    "open":  0.043790000000000003,
    "close":  0.043130000000000002,
    "high":  0.04301,
    "low":  0.04301,
    "average":  0.043459999999999999,
    "vwap":  0.04301,
    "previousClose":  null,
    "volume":  null,
    "baseVolume":  480.600000000000022737,
    "quoteVolume":  20.670605999999999369,
    "bidVolume":  null,
    "askVolume":  null,
    "change":  -0.00066,
    "percentage":  -1.520000000000000018,
    "timestamp":  1767226851451,
    "datetime":  "2026-01-01T00:20:51.451244",
    "exchange_timestamp":  "2026-01-01T00:20:51.451246",
    "data_source":  "official_exchange_api",
    "exchange_id":  "cex"},
  {"token":  "Kaspa",
    "exchange":  "cex",
    "symbol":  "KAS/USDT",
    "last":  0.043139999999999998,
    "bid":  0.04308,
    "ask":  0.043139999999999998,
    "open":  0.043799999999999999,
    "close":  0.043139999999999998,
    "high":  0.04301,
    "low":  0.04301,
    "average":  0.043470000000000002,
    "vwap":  0.04301,
    "previousClose":  null,
    "volume":  null,
    "baseVolume":  480.600000000000022737,
    "quoteVolume":  20.670605999999999369,
    "bidVolume":  null,
    "askVolume":  null,
    "change":  -0.00066,
    "percentage":  -1.5,
    "timestamp":  1767226874779,
    "datetime":  "2026-01-01T00:21:14.779459",
    "exchange_timestamp":  "2026-01-01T00:21:14.779461",
    "data_source":  "official_exchange_api",
    "exchange_id":  "cex"},
  {"token":  "Kaspa",
    "exchange":  "cex",
    "symbol":  "KAS/USDT",
    "last":  0.043130000000000002,
    "bid":  0.04308,
    "ask":  0.043130000000000002,
    "open":  0.043819999999999998,
    "close":  0.043130000000000002,
    "high":  0.04301,
    "low":  0.04301,
    "average":  0.043470000000000002,
    "vwap":  0.04301,
    "previousClose":  null,
    "volume":  null,
    "baseVolume":  480.600000000000022737,
    "quoteVolume":  20.670605999999999369,
    "bidVolume":  null,
    "askVolume":  null,
    "change":  -0.00069,
    "percentage":  -1.59000000000000008,
    "timestamp":  1767226919942,
    "datetime":  "2026-01-01T00:21:59.942797",
    "exchange_timestamp":  "2026-01-01T00:21:59.942798",
    "data_source":  "official_exchange_api",
    "exchange_id":  "cex"},
  {"token":  "Kaspa",
    "exchange":  "cex",
    "symbol":  "KAS/USDT",
    "last":  0.043139999999999998,
    "bid":  0.04308,
    "ask":  0.043139999999999998,
    "open":  0.043830000000000001,
    "close":  0.043139999999999998,
    "high":  0.04301,
    "low":  0.04301,
    "average":  0.043479999999999998,
    "vwap":  0.04301,
    "previousClose":  null,
    "volume":  null,
    "baseVolume":  480.600000000000022737,
    "quoteVolume":  20.670605999999999369,
    "bidVolume":  null,
    "askVolume":  null,
    "change":  -0.00069,
    "percentage":  -1.570000000000000062,
    "timestamp":  1767226963077,
    "datetime":  "2026-01-01T00:22:43.077183",
    "exchange_timestamp":  "2026-01-01T00:22:43.077186",
    "data_source":  "official_exchange_api",
    "exchange_id":  "cex"},
  {"token":  "Kaspa",
    "exchange":  "cex",
    "symbol":  "KAS/USDT",
    "last":  0.04317,
    "bid":  0.043110000000000002,
    "ask":  0.04317,
    "open":  0.043830000000000001,
    "close":  0.04317,
    "high":  0.04301,
    "low":  0.04301,
    "average":  0.043499999999999997,
    "vwap":  0.04301,
    "previousClose":  null,
    "volume":  null,
    "baseVolume":  480.600000000000022737,
    "quoteVolume":  20.670605999999999369,
    "bidVolume":  null,
    "askVolume":  null,
    "change":  -0.00066,
    "percentage":  -1.5,
    "timestamp":  1767227004080,
    "datetime":  "2026-01-01T00:23:24.080339",
    "exchange_timestamp":  "2026-01-01T00:23:24.080341",
    "data_source":  "official_exchange_api",
    "exchange_id":  "cex"},
  {"token":  "Kaspa",
    "exchange":  "cex",
    "symbol":  "KAS/USDT",
    "last":  0.043150000000000001,
    "bid":  0.04308,
    "ask":  0.043150000000000001,
    "open":  0.043839999999999997,
    "close":  0.043150000000000001,
    "high":  0.04301,
    "low":  0.04301,
    "average":  0.043490000000000001,
    "vwap":  0.04301,
    "previousClose":  null,
    "volume":  null,
    "baseVolume":  480.600000000000022737,
    "quoteVolume":  20.670605999999999369,
    "bidVolume":  null,
    "askVolume":  null,
    "change":  -0.00069,
    "percentage":  -1.59000000000000008,
    "timestamp":  1767227066245,
    "datetime":  "2026-01-01T00:24:26.245545",
    "exchange_timestamp":  "2026-01-01T00:24:26.245547",
    "data_source":  "official_exchange_api",
    "exchange_id":  "cex"},
  {"token":  "Kaspa",
    "exchange":  "cex",
    "symbol":  "KAS/USDT",
    "last":  0.043150000000000001,
    "bid":  0.043090000000000003,
    "ask":  0.043150000000000001,
    "open":  0.043839999999999997,
    "close":  0.043150000000000001,
    "high":  0.04301,
    "low":  0.04301,
    "average":  0.043490000000000001,
    "vwap":  0.04301,
    "previousClose":  null,
    "volume":  null,
    "baseVolume":  480.600000000000022737,
    "quoteVolume":  20.670605999999999369,
    "bidVolume":  null,
    "askVolume":  null,
    "change":  -0.00069,
    "percentage":  -1.59000000000000008,
    "timestamp":  1767227079155,
    "datetime":  "2026-01-01T00:24:39.155108",
    "exchange_timestamp":  "2026-01-01T00:24:39.155111",
    "data_source":  "official_exchange_api",
    "exchange_id":  "cex"},
  {"token":  "Kaspa",
    "exchange":  "cex",
    "symbol":  "KAS/USDT",
    "last":  0.043180000000000003,
    "bid":  0.043119999999999999,
    "ask":  0.043180000000000003,
    "open":  0.043830000000000001,
    "close":  0.043180000000000003,
    "high":  0.04301,
    "low":  0.04301,
    "average":  0.043499999999999997,
    "vwap":  0.04301,
    "previousClose":  null,
    "volume":  null,
    "baseVolume":  480.600000000000022737,
    "quoteVolume":  20.670605999999999369,
    "bidVolume":  null,
    "askVolume":  null,
    "change":  -0.00065,
    "percentage":  -1.5,
    "timestamp":  1767227151276,
    "datetime":  "2026-01-01T00:25:51.276195",
    "exchange_timestamp":  "2026-01-01T00:25:51.276198",
    "data_source":  "official_exchange_api",
    "exchange_id":  "cex"},
  {"token":  "Kaspa",
    "exchange":  "cex",
    "symbol":  "KAS/USDT",
    "last":  0.043150000000000001,
    "bid":  0.043090000000000003,
    "ask":  0.043150000000000001,
    "open":  0.043830000000000001,
    "close":  0.043150000000000001,
    "high":  0.04301,
    "low":  0.04301,
    "average":  0.043490000000000001,
    "vwap":  0.04301,
    "previousClose":  null,
    "volume":  null,
    "baseVolume":  480.600000000000022737,
    "quoteVolume":  20.670605999999999369,
    "bidVolume":  null,
    "askVolume":  null,
    "change":  -0.00068,
    "percentage":  -1.570000000000000062,
    "timestamp":  1767227156517,
    "datetime":  "2026-01-01T00:25:56.517321",
    "exchange_timestamp":  "2026-01-01T00:25:56.517323",
    "data_source":  "official_exchange_api",
    "exchange_id":  "cex"},
  {"token":  "Kaspa",
    "exchange":  "cex",
    "symbol":  "KAS/USDT",
    "last":  0.043110000000000002,
    "bid":  0.043049999999999998,
    "ask":  0.043110000000000002,
    "open":  0.043830000000000001,
    "close":  0.043110000000000002,
    "high":  0.04301,
    "low":  0.04301,
    "average":  0.043470000000000002,
    "vwap":  0.04301,
    "previousClose":  null,
    "volume":  null,
    "baseVolume":  480.600000000000022737,
    "quoteVolume":  20.670605999999999369,
    "bidVolume":  null,
    "askVolume":  null,
    "change":  -0.00072,
    "percentage":  -1.65999999999999992,
    "timestamp":  1767227210150,
    "datetime":  "2026-01-01T00:26:50.150808",
    "exchange_timestamp":  "2026-01-01T00:26:50.150810",
    "data_source":  "official_exchange_api",
    "exchange_id":  "cex"},
  {"token":  "Kaspa",
    "exchange":  "cex",
    "symbol":  "KAS/USDT",
    "last":  0.043119999999999999,
    "bid":  0.043060000000000001,
    "ask":  0.043119999999999999,
    "open":  0.043830000000000001,
    "close":  0.043119999999999999,
    "high":  0.04301,
    "low":  0.04301,
    "average":  0.043470000000000002,
    "vwap":  0.04301,
    "previousClose":  null,
    "volume":  null,
    "baseVolume":  480.600000000000022737,
    "quoteVolume":  20.670605999999999369,
    "bidVolume":  null,
    "askVolume":  null,
    "change":  -0.00071,
    "percentage":  -1.639999999999999902,
    "timestamp":  1767227253102,
    "datetime":  "2026-01-01T00:27:33.102961",
    "exchange_timestamp":  "2026-01-01T00:27:33.102963",
    "data_source":  "official_exchange_api",
    "exchange_id":  "cex"},
  {"token":  "Kaspa",
    "exchange":  "cex",
    "symbol":  "KAS/USDT",
    "last":  0.043150000000000001,
    "bid":  0.043099999999999999,
    "ask":  0.043150000000000001,
    "open":  0.043830000000000001,
    "close":  0.043150000000000001,
    "high":  0.04301,
    "low":  0.04301,
    "average":  0.043490000000000001,
    "vwap":  0.04301,
    "previousClose":  null,
    "volume":  null,
    "baseVolume":  480.600000000000022737,
    "quoteVolume":  20.670605999999999369,
    "bidVolume":  null,
    "askVolume":  null,
    "change":  -0.00068,
    "percentage":  -1.570000000000000062,
    "timestamp":  1767227280074,
    "datetime":  "2026-01-01T00:28:00.074155",
    "exchange_timestamp":  "2026-01-01T00:28:00.074156",
    "data_source":  "official_exchange_api",
    "exchange_id":  "cex"},
  {"token":  "Kaspa",
    "exchange":  "cex",
    "symbol":  "KAS/USDT",
    "last":  0.04317,
    "bid":  0.043119999999999999,
    "ask":  0.04317,
    "open":  0.043830000000000001,
    "close":  0.04317,
    "high":  0.04301,
    "low":  0.04301,
    "average":  0.043499999999999997,
    "vwap":  0.04301,
    "previousClose":  null,
    "volume":  null,
    "baseVolume":  480.600000000000022737,
    "quoteVolume":  20.670605999999999369,
    "bidVolume":  null,
    "askVolume":  null,
    "change":  -0.00066,
    "percentage":  -1.520000000000000018,
    "timestamp":  1767227350344,
    "datetime":  "2026-01-01T00:29:10.344176",
    "exchange_timestamp":  "2026-01-01T00:29:10.344178",
    "data_source":  "official_exchange_api",
    "exchange_id":  "cex"},
  {"token":  "Kaspa",
    "exchange":  "cex",
    "symbol":  "KAS/USDT",
    "last":  0.04317,
    "bid":  0.043119999999999999,
    "ask":  0.04317,
    "open":  0.043830000000000001,
    "close":  0.04317,
    "high":  0.04301,
    "low":  0.04301,
    "average":  0.043499999999999997,
    "vwap":  0.04301,
    "previousClose":  null,
    "volume":  null,
    "baseVolume":  480.600000000000022737,
    "quoteVolume":  20.670605999999999369,
    "bidVolume":  null,
    "askVolume":  null,
    "change":  -0.00066,
    "percentage":  -1.520000000000000018,
    "timestamp":  1767227351272,
    "datetime":  "2026-01-01T00:29:11.272441",
    "exchange_timestamp":  "2026-01-01T00:29:11.272443",
    "data_source":  "official_exchange_api",
    "exchange_id":  "cex"},
  {"token":  "Kaspa",
    "exchange":  "cex",
    "symbol":  "KAS/USDT",
    "last":  0.043159999999999997,
    "bid":  0.043110000000000002,
    "ask":  0.043159999999999997,
    "open":  0.043889999999999998,
    "close":  0.043159999999999997,
    "high":  0.04301,
    "low":  0.04301,
    "average":  0.043520000000000003,
    "vwap":  0.04301,
    "previousClose":  null,
    "volume":  null,
    "baseVolume":  480.600000000000022737,
    "quoteVolume":  20.670605999999999369,
    "bidVolume":  null,
    "askVolume":  null,
    "change":  -0.00073,
    "percentage":  -1.65999999999999992,
    "timestamp":  1767227419810,
    "datetime":  "2026-01-01T00:30:19.810540",
    "exchange_timestamp":  "2026-01-01T00:30:19.810542",
    "data_source":  "official_exchange_api",
    "exchange_id":  "cex"},
  {"token":  "Kaspa",
    "exchange":  "cex",
    "symbol":  "KAS/USDT",
    "last":  0.043159999999999997,
    "bid":  0.043110000000000002,
    "ask":  0.043159999999999997,
    "open":  0.043889999999999998,
    "close":  0.043159999999999997,
    "high":  0.04301,
    "low":  0.04301,
    "average":  0.043520000000000003,
    "vwap":  0.04301,
    "previousClose":  null,
    "volume":  null,
    "baseVolume":  480.600000000000022737,
    "quoteVolume":  20.670605999999999369,
    "bidVolume":  null,
    "askVolume":  null,
    "change":  -0.00073,
    "percentage":  -1.65999999999999992,
    "timestamp":  1767227452300,
    "datetime":  "2026-01-01T00:30:52.300613",
    "exchange_timestamp":  "2026-01-01T00:30:52.300616",
    "data_source":  "official_exchange_api",
    "exchange_id":  "cex"},
  {"token":  "Kaspa",
    "exchange":  "cex",
    "symbol":  "KAS/USDT",
    "last":  0.043180000000000003,
    "bid":  0.043130000000000002,
    "ask":  0.043180000000000003,
    "open":  0.043830000000000001,
    "close":  0.043180000000000003,
    "high":  0.04301,
    "low":  0.04301,
    "average":  0.043499999999999997,
    "vwap":  0.04301,
    "previousClose":  null,
    "volume":  null,
    "baseVolume":  480.600000000000022737,
    "quoteVolume":  20.670605999999999369,
    "bidVolume":  null,
    "askVolume":  null,
    "change":  -0.00065,
    "percentage":  -1.5,
    "timestamp":  1767227490796,
    "datetime":  "2026-01-01T00:31:30.796991",
    "exchange_timestamp":  "2026-01-01T00:31:30.796993",
    "data_source":  "official_exchange_api",
    "exchange_id":  "cex"},
  {"token":  "Kaspa",
    "exchange":  "cex",
    "symbol":  "KAS/USDT",
    "last":  0.04317,
    "bid":  0.043110000000000002,
    "ask":  0.04317,
    "open":  0.043830000000000001,
    "close":  0.04317,
    "high":  0.04301,
    "low":  0.04301,
    "average":  0.043499999999999997,
    "vwap":  0.04301,
    "previousClose":  null,
    "volume":  null,
    "baseVolume":  480.600000000000022737,
    "quoteVolume":  20.670605999999999369,
    "bidVolume":  null,
    "askVolume":  null,
    "change":  -0.00066,
    "percentage":  -1.520000000000000018,
    "timestamp":  1767227543583,
    "datetime":  "2026-01-01T00:32:23.583365",
    "exchange_timestamp":  "2026-01-01T00:32:23.583367",
    "data_source":  "official_exchange_api",
    "exchange_id":  "cex"},
  {"token":  "Kaspa",
    "exchange":  "cex",
    "symbol":  "KAS/USDT",
    "last":  0.043180000000000003,
    "bid":  0.043119999999999999,
    "ask":  0.043180000000000003,
    "open":  0.043830000000000001,
    "close":  0.043180000000000003,
    "high":  0.04301,
    "low":  0.04301,
    "average":  0.043499999999999997,
    "vwap":  0.04301,
    "previousClose":  null,
    "volume":  null,
    "baseVolume":  480.600000000000022737,
    "quoteVolume":  20.670605999999999369,
    "bidVolume":  null,
    "askVolume":  null,
    "change":  -0.00065,
    "percentage":  -1.5,
    "timestamp":  1767227548252,
    "datetime":  "2026-01-01T00:32:28.252962",
    "exchange_timestamp":  "2026-01-01T00:32:28.252964",
    "data_source":  "official_exchange_api",
    "exchange_id":  "cex"},
  {"token":  "Kaspa",
    "exchange":  "cex",
    "symbol":  "KAS/USDT",
    "last":  0.04317,
    "bid":  0.043110000000000002,
    "ask":  0.04317,
    "open":  0.043830000000000001,
    "close":  0.04317,
    "high":  0.04301,
    "low":  0.04301,
    "average":  0.043499999999999997,
    "vwap":  0.04301,
    "previousClose":  null,
    "volume":  null,
    "baseVolume":  480.600000000000022737,
    "quoteVolume":  20.670605999999999369,
    "bidVolume":  null,
    "askVolume":  null,
    "change":  -0.00066,
    "percentage":  -1.5,
    "timestamp":  1767227609332,
    "datetime":  "2026-01-01T00:33:29.332287",
    "exchange_timestamp":  "2026-01-01T00:33:29.332289",
    "data_source":  "official_exchange_api",
    "exchange_id":  "cex"},
  {"token":  "Kaspa",
    "exchange":  "cex",
    "symbol":  "KAS/USDT",
    "last":  0.043249999999999997,
    "bid":  0.043189999999999999,
    "ask":  0.043249999999999997,
    "open":  0.043830000000000001,
    "close":  0.043249999999999997,
    "high":  0.04301,
    "low":  0.04301,
    "average":  0.043540000000000002,
    "vwap":  0.04301,
    "previousClose":  null,
    "volume":  null,
    "baseVolume":  480.600000000000022737,
    "quoteVolume":  20.670605999999999369,
    "bidVolume":  null,
    "askVolume":  null,
    "change":  -0.00058,
    "percentage":  -1.320000000000000062,
    "timestamp":  1767227633108,
    "datetime":  "2026-01-01T00:33:53.108438",
    "exchange_timestamp":  "2026-01-01T00:33:53.108439",
    "data_source":  "official_exchange_api",
    "exchange_id":  "cex"},
  {"token":  "Kaspa",
    "exchange":  "cex",
    "symbol":  "KAS/USDT",
    "last":  0.04326,
    "bid":  0.043200000000000002,
    "ask":  0.04326,
    "open":  0.043830000000000001,
    "close":  0.04326,
    "high":  0.04301,
    "low":  0.04301,
    "average":  0.043540000000000002,
    "vwap":  0.04301,
    "previousClose":  null,
    "volume":  null,
    "baseVolume":  480.600000000000022737,
    "quoteVolume":  20.670605999999999369,
    "bidVolume":  null,
    "askVolume":  null,
    "change":  -0.00057,
    "percentage":  -1.300000000000000044,
    "timestamp":  1767227676112,
    "datetime":  "2026-01-01T00:34:36.112097",
    "exchange_timestamp":  "2026-01-01T00:34:36.112099",
    "data_source":  "official_exchange_api",
    "exchange_id":  "cex"},
  {"token":  "Kaspa",
    "exchange":  "cex",
    "symbol":  "KAS/USDT",
    "last":  0.043209999999999998,
    "bid":  0.043150000000000001,
    "ask":  0.043209999999999998,
    "open":  0.043889999999999998,
    "close":  0.043209999999999998,
    "high":  0.04301,
    "low":  0.04301,
    "average":  0.043549999999999998,
    "vwap":  0.04301,
    "previousClose":  null,
    "volume":  null,
    "baseVolume":  480.600000000000022737,
    "quoteVolume":  20.670605999999999369,
    "bidVolume":  null,
    "askVolume":  null,
    "change":  -0.00068,
    "percentage":  -1.540000000000000036,
    "timestamp":  1767227719065,
    "datetime":  "2026-01-01T00:35:19.065149",
    "exchange_timestamp":  "2026-01-01T00:35:19.065151",
    "data_source":  "official_exchange_api",
    "exchange_id":  "cex"},
  {"token":  "Kaspa",
    "exchange":  "cex",
    "symbol":  "KAS/USDT",
    "last":  0.043209999999999998,
    "bid":  0.043139999999999998,
    "ask":  0.043209999999999998,
    "open":  0.043889999999999998,
    "close":  0.043209999999999998,
    "high":  0.04301,
    "low":  0.04301,
    "average":  0.043549999999999998,
    "vwap":  0.04301,
    "previousClose":  null,
    "volume":  null,
    "baseVolume":  480.600000000000022737,
    "quoteVolume":  20.670605999999999369,
    "bidVolume":  null,
    "askVolume":  null,
    "change":  -0.00068,
    "percentage":  -1.540000000000000036,
    "timestamp":  1767227736095,
    "datetime":  "2026-01-01T00:35:36.095748",
    "exchange_timestamp":  "2026-01-01T00:35:36.095750",
    "data_source":  "official_exchange_api",
    "exchange_id":  "cex"},
  {"token":  "Kaspa",
    "exchange":  "cex",
    "symbol":  "KAS/USDT",
    "last":  0.043139999999999998,
    "bid":  0.043090000000000003,
    "ask":  0.043139999999999998,
    "open":  0.043889999999999998,
    "close":  0.043139999999999998,
    "high":  0.04301,
    "low":  0.04301,
    "average":  0.04351,
    "vwap":  0.04301,
    "previousClose":  null,
    "volume":  null,
    "baseVolume":  480.600000000000022737,
    "quoteVolume":  20.670605999999999369,
    "bidVolume":  null,
    "askVolume":  null,
    "change":  -0.00075,
    "percentage":  -1.699999999999999956,
    "timestamp":  1767227815584,
    "datetime":  "2026-01-01T00:36:55.584374",
    "exchange_timestamp":  "2026-01-01T00:36:55.584377",
    "data_source":  "official_exchange_api",
    "exchange_id":  "cex"},
  {"token":  "Kaspa",
    "exchange":  "cex",
    "symbol":  "KAS/USDT",
    "last":  0.043130000000000002,
    "bid":  0.04308,
    "ask":  0.043130000000000002,
    "open":  0.043880000000000002,
    "close":  0.043130000000000002,
    "high":  0.04301,
    "low":  0.04301,
    "average":  0.043499999999999997,
    "vwap":  0.04301,
    "previousClose":  null,
    "volume":  null,
    "baseVolume":  480.600000000000022737,
    "quoteVolume":  20.670605999999999369,
    "bidVolume":  null,
    "askVolume":  null,
    "change":  -0.00075,
    "percentage":  -1.729999999999999982,
    "timestamp":  1767227820904,
    "datetime":  "2026-01-01T00:37:00.904050",
    "exchange_timestamp":  "2026-01-01T00:37:00.904053",
    "data_source":  "official_exchange_api",
    "exchange_id":  "cex"},
  {"token":  "Kaspa",
    "exchange":  "cex",
    "symbol":  "KAS/USDT",
    "last":  0.043130000000000002,
    "bid":  0.04308,
    "ask":  0.043130000000000002,
    "open":  0.043880000000000002,
    "close":  0.043130000000000002,
    "high":  0.04301,
    "low":  0.04301,
    "average":  0.043499999999999997,
    "vwap":  0.04301,
    "previousClose":  null,
    "volume":  null,
    "baseVolume":  480.600000000000022737,
    "quoteVolume":  20.670605999999999369,
    "bidVolume":  null,
    "askVolume":  null,
    "change":  -0.00075,
    "percentage":  -1.729999999999999982,
    "timestamp":  1767227872934,
    "datetime":  "2026-01-01T00:37:52.934545",
    "exchange_timestamp":  "2026-01-01T00:37:52.934547",
    "data_source":  "official_exchange_api",
    "exchange_id":  "cex"},
  {"token":  "Kaspa",
    "exchange":  "cex",
    "symbol":  "KAS/USDT",
    "last":  0.043130000000000002,
    "bid":  0.043069999999999997,
    "ask":  0.043130000000000002,
    "open":  0.043909999999999998,
    "close":  0.043130000000000002,
    "high":  0.04301,
    "low":  0.04301,
    "average":  0.043520000000000003,
    "vwap":  0.04301,
    "previousClose":  null,
    "volume":  null,
    "baseVolume":  480.600000000000022737,
    "quoteVolume":  20.670605999999999369,
    "bidVolume":  null,
    "askVolume":  null,
    "change":  -0.00078,
    "percentage":  -1.790000000000000036,
    "timestamp":  1767227917809,
    "datetime":  "2026-01-01T00:38:37.809152",
    "exchange_timestamp":  "2026-01-01T00:38:37.809154",
    "data_source":  "official_exchange_api",
    "exchange_id":  "cex"},
  {"token":  "Kaspa",
    "exchange":  "cex",
    "symbol":  "KAS/USDT",
    "last":  0.043119999999999999,
    "bid":  0.043069999999999997,
    "ask":  0.043119999999999999,
    "open":  0.043920000000000001,
    "close":  0.043119999999999999,
    "high":  0.04301,
    "low":  0.04301,
    "average":  0.043520000000000003,
    "vwap":  0.04301,
    "previousClose":  null,
    "volume":  null,
    "baseVolume":  480.600000000000022737,
    "quoteVolume":  20.670605999999999369,
    "bidVolume":  null,
    "askVolume":  null,
    "change":  -0.0008,
    "percentage":  -1.820000000000000062,
    "timestamp":  1767227943578,
    "datetime":  "2026-01-01T00:39:03.578475",
    "exchange_timestamp":  "2026-01-01T00:39:03.578477",
    "data_source":  "official_exchange_api",
    "exchange_id":  "cex"},
  {"token":  "Kaspa",
    "exchange":  "cex",
    "symbol":  "KAS/USDT",
    "last":  0.043060000000000001,
    "bid":  0.042999999999999997,
    "ask":  0.043060000000000001,
    "open":  0.043909999999999998,
    "close":  0.043060000000000001,
    "high":  0.04301,
    "low":  0.04301,
    "average":  0.043479999999999998,
    "vwap":  0.04301,
    "previousClose":  null,
    "volume":  null,
    "baseVolume":  480.600000000000022737,
    "quoteVolume":  20.670605999999999369,
    "bidVolume":  null,
    "askVolume":  null,
    "change":  -0.00085,
    "percentage":  -1.949999999999999956,
    "timestamp":  1767228004065,
    "datetime":  "2026-01-01T00:40:04.065525",
    "exchange_timestamp":  "2026-01-01T00:40:04.065527",
    "data_source":  "official_exchange_api",
    "exchange_id":  "cex"},
  {"token":  "Kaspa",
    "exchange":  "cex",
    "symbol":  "KAS/USDT",
    "last":  0.043090000000000003,
    "bid":  0.043029999999999999,
    "ask":  0.043090000000000003,
    "open":  0.043909999999999998,
    "close":  0.043090000000000003,
    "high":  0.04301,
    "low":  0.04301,
    "average":  0.043499999999999997,
    "vwap":  0.04301,
    "previousClose":  null,
    "volume":  null,
    "baseVolume":  480.600000000000022737,
    "quoteVolume":  20.670605999999999369,
    "bidVolume":  null,
    "askVolume":  null,
    "change":  -0.00082,
    "percentage":  -1.879999999999999893,
    "timestamp":  1767228013838,
    "datetime":  "2026-01-01T00:40:13.838538",
    "exchange_timestamp":  "2026-01-01T00:40:13.838540",
    "data_source":  "official_exchange_api",
    "exchange_id":  "cex"},
  {"token":  "Kaspa",
    "exchange":  "cex",
    "symbol":  "KAS/USDT",
    "last":  0.043110000000000002,
    "bid":  0.043049999999999998,
    "ask":  0.043110000000000002,
    "open":  0.043869999999999999,
    "close":  0.043110000000000002,
    "high":  0.04301,
    "low":  0.04301,
    "average":  0.043490000000000001,
    "vwap":  0.04301,
    "previousClose":  null,
    "volume":  null,
    "baseVolume":  480.600000000000022737,
    "quoteVolume":  20.670605999999999369,
    "bidVolume":  null,
    "askVolume":  null,
    "change":  -0.00076,
    "percentage":  -1.75,
    "timestamp":  1767228066158,
    "datetime":  "2026-01-01T00:41:06.158403",
    "exchange_timestamp":  "2026-01-01T00:41:06.158406",
    "data_source":  "official_exchange_api",
    "exchange_id":  "cex"},
  {"token":  "Kaspa",
    "exchange":  "cex",
    "symbol":  "KAS/USDT",
    "last":  0.043110000000000002,
    "bid":  0.043049999999999998,
    "ask":  0.043110000000000002,
    "open":  0.043869999999999999,
    "close":  0.043110000000000002,
    "high":  0.04301,
    "low":  0.04301,
    "average":  0.043490000000000001,
    "vwap":  0.04301,
    "previousClose":  null,
    "volume":  null,
    "baseVolume":  480.600000000000022737,
    "quoteVolume":  20.670605999999999369,
    "bidVolume":  null,
    "askVolume":  null,
    "change":  -0.00076,
    "percentage":  -1.75,
    "timestamp":  1767228092913,
    "datetime":  "2026-01-01T00:41:32.913330",
    "exchange_timestamp":  "2026-01-01T00:41:32.913332",
    "data_source":  "official_exchange_api",
    "exchange_id":  "cex"},
  {"token":  "Kaspa",
    "exchange":  "cex",
    "symbol":  "KAS/USDT",
    "last":  0.043110000000000002,
    "bid":  0.043049999999999998,
    "ask":  0.043110000000000002,
    "open":  0.043869999999999999,
    "close":  0.043110000000000002,
    "high":  0.04301,
    "low":  0.04301,
    "average":  0.043490000000000001,
    "vwap":  0.04301,
    "previousClose":  null,
    "volume":  null,
    "baseVolume":  480.600000000000022737,
    "quoteVolume":  20.670605999999999369,
    "bidVolume":  null,
    "askVolume":  null,
    "change":  -0.00076,
    "percentage":  -1.75,
    "timestamp":  1767228126761,
    "datetime":  "2026-01-01T00:42:06.761968",
    "exchange_timestamp":  "2026-01-01T00:42:06.761970",
    "data_source":  "official_exchange_api",
    "exchange_id":  "cex"},
  {"token":  "Kaspa",
    "exchange":  "cex",
    "symbol":  "KAS/USDT",
    "last":  0.043099999999999999,
    "bid":  0.043049999999999998,
    "ask":  0.043099999999999999,
    "open":  0.043860000000000003,
    "close":  0.043099999999999999,
    "high":  0.04301,
    "low":  0.04301,
    "average":  0.043479999999999998,
    "vwap":  0.04301,
    "previousClose":  null,
    "volume":  null,
    "baseVolume":  480.600000000000022737,
    "quoteVolume":  20.670605999999999369,
    "bidVolume":  null,
    "askVolume":  null,
    "change":  -0.00076,
    "percentage":  -1.729999999999999982,
    "timestamp":  1767228184682,
    "datetime":  "2026-01-01T00:43:04.682305",
    "exchange_timestamp":  "2026-01-01T00:43:04.682307",
    "data_source":  "official_exchange_api",
    "exchange_id":  "cex"},
  {"token":  "Kaspa",
    "exchange":  "cex",
    "symbol":  "KAS/USDT",
    "last":  0.04308,
    "bid":  0.043020000000000003,
    "ask":  0.04308,
    "open":  0.043860000000000003,
    "close":  0.04308,
    "high":  0.04301,
    "low":  0.04301,
    "average":  0.043470000000000002,
    "vwap":  0.04301,
    "previousClose":  null,
    "volume":  null,
    "baseVolume":  480.600000000000022737,
    "quoteVolume":  20.670605999999999369,
    "bidVolume":  null,
    "askVolume":  null,
    "change":  -0.00078,
    "percentage":  -1.770000000000000018,
    "timestamp":  1767228200034,
    "datetime":  "2026-01-01T00:43:20.034013",
    "exchange_timestamp":  "2026-01-01T00:43:20.034015",
    "data_source":  "official_exchange_api",
    "exchange_id":  "cex"},
  {"token":  "Kaspa",
    "exchange":  "cex",
    "symbol":  "KAS/USDT",
    "last":  0.043060000000000001,
    "bid":  0.042999999999999997,
    "ask":  0.043060000000000001,
    "open":  0.043860000000000003,
    "close":  0.043060000000000001,
    "high":  0.04301,
    "low":  0.04301,
    "average":  0.043459999999999999,
    "vwap":  0.04301,
    "previousClose":  null,
    "volume":  null,
    "baseVolume":  480.600000000000022737,
    "quoteVolume":  20.670605999999999369,
    "bidVolume":  null,
    "askVolume":  null,
    "change":  -0.0008,
    "percentage":  -1.820000000000000062,
    "timestamp":  1767228264526,
    "datetime":  "2026-01-01T00:44:24.526890",
    "exchange_timestamp":  "2026-01-01T00:44:24.526892",
    "data_source":  "official_exchange_api",
    "exchange_id":  "cex"},
  {"token":  "Kaspa",
    "exchange":  "cex",
    "symbol":  "KAS/USDT",
    "last":  0.043069999999999997,
    "bid":  0.04301,
    "ask":  0.043069999999999997,
    "open":  0.043860000000000003,
    "close":  0.043069999999999997,
    "high":  0.04301,
    "low":  0.04301,
    "average":  0.043459999999999999,
    "vwap":  0.04301,
    "previousClose":  null,
    "volume":  null,
    "baseVolume":  480.600000000000022737,
    "quoteVolume":  20.670605999999999369,
    "bidVolume":  null,
    "askVolume":  null,
    "change":  -0.00079,
    "percentage":  -1.800000000000000044,
    "timestamp":  1767228270536,
    "datetime":  "2026-01-01T00:44:30.536358",
    "exchange_timestamp":  "2026-01-01T00:44:30.536360",
    "data_source":  "official_exchange_api",
    "exchange_id":  "cex"},
  {"token":  "Kaspa",
    "exchange":  "cex",
    "symbol":  "KAS/USDT",
    "last":  0.043069999999999997,
    "bid":  0.043020000000000003,
    "ask":  0.043069999999999997,
    "open":  0.043860000000000003,
    "close":  0.043069999999999997,
    "high":  0.04301,
    "low":  0.04301,
    "average":  0.043459999999999999,
    "vwap":  0.04301,
    "previousClose":  null,
    "volume":  null,
    "baseVolume":  480.600000000000022737,
    "quoteVolume":  20.670605999999999369,
    "bidVolume":  null,
    "askVolume":  null,
    "change":  -0.00079,
    "percentage":  -1.800000000000000044,
    "timestamp":  1767228322870,
    "datetime":  "2026-01-01T00:45:22.870051",
    "exchange_timestamp":  "2026-01-01T00:45:22.870053",
    "data_source":  "official_exchange_api",
    "exchange_id":  "cex"},
  {"token":  "Kaspa",
    "exchange":  "cex",
    "symbol":  "KAS/USDT",
    "last":  0.043069999999999997,
    "bid":  0.04301,
    "ask":  0.043069999999999997,
    "open":  0.043920000000000001,
    "close":  0.043069999999999997,
    "high":  0.04301,
    "low":  0.04301,
    "average":  0.043490000000000001,
    "vwap":  0.04301,
    "previousClose":  null,
    "volume":  null,
    "baseVolume":  480.600000000000022737,
    "quoteVolume":  20.670605999999999369,
    "bidVolume":  null,
    "askVolume":  null,
    "change":  -0.00085,
    "percentage":  -1.929999999999999938,
    "timestamp":  1767228366914,
    "datetime":  "2026-01-01T00:46:06.914453",
    "exchange_timestamp":  "2026-01-01T00:46:06.914456",
    "data_source":  "official_exchange_api",
    "exchange_id":  "cex"},
  {"token":  "Kaspa",
    "exchange":  "cex",
    "symbol":  "KAS/USDT",
    "last":  0.043060000000000001,
    "bid":  0.042999999999999997,
    "ask":  0.043060000000000001,
    "open":  0.043909999999999998,
    "close":  0.043060000000000001,
    "high":  0.04301,
    "low":  0.04301,
    "average":  0.043479999999999998,
    "vwap":  0.04301,
    "previousClose":  null,
    "volume":  null,
    "baseVolume":  480.600000000000022737,
    "quoteVolume":  20.670605999999999369,
    "bidVolume":  null,
    "askVolume":  null,
    "change":  -0.00085,
    "percentage":  -1.949999999999999956,
    "timestamp":  1767228395673,
    "datetime":  "2026-01-01T00:46:35.673023",
    "exchange_timestamp":  "2026-01-01T00:46:35.673024",
    "data_source":  "official_exchange_api",
    "exchange_id":  "cex"},
  {"token":  "Kaspa",
    "exchange":  "cex",
    "symbol":  "KAS/USDT",
    "last":  0.043069999999999997,
    "bid":  0.04301,
    "ask":  0.043069999999999997,
    "open":  0.043920000000000001,
    "close":  0.043069999999999997,
    "high":  0.04301,
    "low":  0.04301,
    "average":  0.043490000000000001,
    "vwap":  0.04301,
    "previousClose":  null,
    "volume":  null,
    "baseVolume":  480.600000000000022737,
    "quoteVolume":  20.670605999999999369,
    "bidVolume":  null,
    "askVolume":  null,
    "change":  -0.00085,
    "percentage":  -1.929999999999999938,
    "timestamp":  1767228454128,
    "datetime":  "2026-01-01T00:47:34.128698",
    "exchange_timestamp":  "2026-01-01T00:47:34.128701",
    "data_source":  "official_exchange_api",
    "exchange_id":  "cex"},
  {"token":  "Kaspa",
    "exchange":  "cex",
    "symbol":  "KAS/USDT",
    "last":  0.043069999999999997,
    "bid":  0.04301,
    "ask":  0.043069999999999997,
    "open":  0.043920000000000001,
    "close":  0.043069999999999997,
    "high":  0.04301,
    "low":  0.04301,
    "average":  0.043490000000000001,
    "vwap":  0.04301,
    "previousClose":  null,
    "volume":  null,
    "baseVolume":  480.600000000000022737,
    "quoteVolume":  20.670605999999999369,
    "bidVolume":  null,
    "askVolume":  null,
    "change":  -0.00085,
    "percentage":  -1.929999999999999938,
    "timestamp":  1767228458962,
    "datetime":  "2026-01-01T00:47:38.962061",
    "exchange_timestamp":  "2026-01-01T00:47:38.962064",
    "data_source":  "official_exchange_api",
    "exchange_id":  "cex"},
  {"token":  "Kaspa",
    "exchange":  "cex",
    "symbol":  "KAS/USDT",
    "last":  0.043090000000000003,
    "bid":  0.043029999999999999,
    "ask":  0.043090000000000003,
    "open":  0.043900000000000002,
    "close":  0.043090000000000003,
    "high":  0.04301,
    "low":  0.04301,
    "average":  0.043490000000000001,
    "vwap":  0.04301,
    "previousClose":  null,
    "volume":  null,
    "baseVolume":  480.600000000000022737,
    "quoteVolume":  20.670605999999999369,
    "bidVolume":  null,
    "askVolume":  null,
    "change":  -0.00081,
    "percentage":  -1.860000000000000098,
    "timestamp":  1767228512932,
    "datetime":  "2026-01-01T00:48:32.932602",
    "exchange_timestamp":  "2026-01-01T00:48:32.932605",
    "data_source":  "official_exchange_api",
    "exchange_id":  "cex"},
  {"token":  "Kaspa",
    "exchange":  "cex",
    "symbol":  "KAS/USDT",
    "last":  0.043090000000000003,
    "bid":  0.043029999999999999,
    "ask":  0.043090000000000003,
    "open":  0.043900000000000002,
    "close":  0.043090000000000003,
    "high":  0.04301,
    "low":  0.04301,
    "average":  0.043490000000000001,
    "vwap":  0.04301,
    "previousClose":  null,
    "volume":  null,
    "baseVolume":  480.600000000000022737,
    "quoteVolume":  20.670605999999999369,
    "bidVolume":  null,
    "askVolume":  null,
    "change":  -0.00081,
    "percentage":  -1.860000000000000098,
    "timestamp":  1767228552974,
    "datetime":  "2026-01-01T00:49:12.974024",
    "exchange_timestamp":  "2026-01-01T00:49:12.974027",
    "data_source":  "official_exchange_api",
    "exchange_id":  "cex"},
  {"token":  "Kaspa",
    "exchange":  "cex",
    "symbol":  "KAS/USDT",
    "last":  0.043099999999999999,
    "bid":  0.043040000000000002,
    "ask":  0.043099999999999999,
    "open":  0.043920000000000001,
    "close":  0.043099999999999999,
    "high":  0.04301,
    "low":  0.04301,
    "average":  0.04351,
    "vwap":  0.04301,
    "previousClose":  null,
    "volume":  null,
    "baseVolume":  480.600000000000022737,
    "quoteVolume":  20.670605999999999369,
    "bidVolume":  null,
    "askVolume":  null,
    "change":  -0.00082,
    "percentage":  -1.879999999999999893,
    "timestamp":  1767228596375,
    "datetime":  "2026-01-01T00:49:56.375581",
    "exchange_timestamp":  "2026-01-01T00:49:56.375583",
    "data_source":  "official_exchange_api",
    "exchange_id":  "cex"},
  {"token":  "Kaspa",
    "exchange":  "cex",
    "symbol":  "KAS/USDT",
    "last":  0.043099999999999999,
    "bid":  0.043040000000000002,
    "ask":  0.043099999999999999,
    "open":  0.043920000000000001,
    "close":  0.043099999999999999,
    "high":  0.04301,
    "low":  0.04301,
    "average":  0.04351,
    "vwap":  0.04301,
    "previousClose":  null,
    "volume":  null,
    "baseVolume":  480.600000000000022737,
    "quoteVolume":  20.670605999999999369,
    "bidVolume":  null,
    "askVolume":  null,
    "change":  -0.00082,
    "percentage":  -1.879999999999999893,
    "timestamp":  1767228654802,
    "datetime":  "2026-01-01T00:50:54.802396",
    "exchange_timestamp":  "2026-01-01T00:50:54.802398",
    "data_source":  "official_exchange_api",
    "exchange_id":  "cex"},
  {"token":  "Kaspa",
    "exchange":  "cex",
    "symbol":  "KAS/USDT",
    "last":  0.043099999999999999,
    "bid":  0.043049999999999998,
    "ask":  0.043099999999999999,
    "open":  0.043920000000000001,
    "close":  0.043099999999999999,
    "high":  0.04301,
    "low":  0.04301,
    "average":  0.04351,
    "vwap":  0.04301,
    "previousClose":  null,
    "volume":  null,
    "baseVolume":  480.600000000000022737,
    "quoteVolume":  20.670605999999999369,
    "bidVolume":  null,
    "askVolume":  null,
    "change":  -0.00082,
    "percentage":  -1.879999999999999893,
    "timestamp":  1767228669403,
    "datetime":  "2026-01-01T00:51:09.403537",
    "exchange_timestamp":  "2026-01-01T00:51:09.403539",
    "data_source":  "official_exchange_api",
    "exchange_id":  "cex"},
  {"token":  "Kaspa",
    "exchange":  "cex",
    "symbol":  "KAS/USDT",
    "last":  0.043110000000000002,
    "bid":  0.043049999999999998,
    "ask":  0.043110000000000002,
    "open":  0.043929999999999997,
    "close":  0.043110000000000002,
    "high":  0.04301,
    "low":  0.04301,
    "average":  0.043520000000000003,
    "vwap":  0.04301,
    "previousClose":  null,
    "volume":  null,
    "baseVolume":  480.600000000000022737,
    "quoteVolume":  20.670605999999999369,
    "bidVolume":  null,
    "askVolume":  null,
    "change":  -0.00082,
    "percentage":  -1.879999999999999893,
    "timestamp":  1767228730219,
    "datetime":  "2026-01-01T00:52:10.219624",
    "exchange_timestamp":  "2026-01-01T00:52:10.219626",
    "data_source":  "official_exchange_api",
    "exchange_id":  "cex"},
  {"token":  "Kaspa",
    "exchange":  "cex",
    "symbol":  "KAS/USDT",
    "last":  0.043110000000000002,
    "bid":  0.043049999999999998,
    "ask":  0.043110000000000002,
    "open":  0.043929999999999997,
    "close":  0.043110000000000002,
    "high":  0.04301,
    "low":  0.04301,
    "average":  0.043520000000000003,
    "vwap":  0.04301,
    "previousClose":  null,
    "volume":  null,
    "baseVolume":  480.600000000000022737,
    "quoteVolume":  20.670605999999999369,
    "bidVolume":  null,
    "askVolume":  null,
    "change":  -0.00082,
    "percentage":  -1.879999999999999893,
    "timestamp":  1767228744865,
    "datetime":  "2026-01-01T00:52:24.865644",
    "exchange_timestamp":  "2026-01-01T00:52:24.865646",
    "data_source":  "official_exchange_api",
    "exchange_id":  "cex"},
  {"token":  "Kaspa",
    "exchange":  "cex",
    "symbol":  "KAS/USDT",
    "last":  0.043090000000000003,
    "bid":  0.043040000000000002,
    "ask":  0.043090000000000003,
    "open":  0.043929999999999997,
    "close":  0.043090000000000003,
    "high":  0.04301,
    "low":  0.04301,
    "average":  0.04351,
    "vwap":  0.04301,
    "previousClose":  null,
    "volume":  null,
    "baseVolume":  480.600000000000022737,
    "quoteVolume":  20.670605999999999369,
    "bidVolume":  null,
    "askVolume":  null,
    "change":  -0.00084,
    "percentage":  -1.929999999999999938,
    "timestamp":  1767228802771,
    "datetime":  "2026-01-01T00:53:22.771358",
    "exchange_timestamp":  "2026-01-01T00:53:22.771360",
    "data_source":  "official_exchange_api",
    "exchange_id":  "cex"},
  {"token":  "Kaspa",
    "exchange":  "cex",
    "symbol":  "KAS/USDT",
    "last":  0.04308,
    "bid":  0.043020000000000003,
    "ask":  0.04308,
    "open":  0.043880000000000002,
    "close":  0.04308,
    "high":  0.04301,
    "low":  0.04301,
    "average":  0.043479999999999998,
    "vwap":  0.04301,
    "previousClose":  null,
    "volume":  null,
    "baseVolume":  480.600000000000022737,
    "quoteVolume":  20.670605999999999369,
    "bidVolume":  null,
    "askVolume":  null,
    "change":  -0.0008,
    "percentage":  -1.820000000000000062,
    "timestamp":  1767228836436,
    "datetime":  "2026-01-01T00:53:56.436588",
    "exchange_timestamp":  "2026-01-01T00:53:56.436590",
    "data_source":  "official_exchange_api",
    "exchange_id":  "cex"},
  {"token":  "Kaspa",
    "exchange":  "cex",
    "symbol":  "KAS/USDT",
    "last":  0.043069999999999997,
    "bid":  0.04301,
    "ask":  0.043069999999999997,
    "open":  0.043880000000000002,
    "close":  0.043069999999999997,
    "high":  0.04301,
    "low":  0.04301,
    "average":  0.043470000000000002,
    "vwap":  0.04301,
    "previousClose":  null,
    "volume":  null,
    "baseVolume":  480.600000000000022737,
    "quoteVolume":  20.670605999999999369,
    "bidVolume":  null,
    "askVolume":  null,
    "change":  -0.00081,
    "percentage":  -1.84000000000000008,
    "timestamp":  1767228869487,
    "datetime":  "2026-01-01T00:54:29.487328",
    "exchange_timestamp":  "2026-01-01T00:54:29.487330",
    "data_source":  "official_exchange_api",
    "exchange_id":  "cex"},
  {"token":  "Kaspa",
    "exchange":  "cex",
    "symbol":  "KAS/USDT",
    "last":  0.043049999999999998,
    "bid":  0.042999999999999997,
    "ask":  0.043049999999999998,
    "open":  0.043889999999999998,
    "close":  0.043049999999999998,
    "high":  0.04301,
    "low":  0.04301,
    "average":  0.043470000000000002,
    "vwap":  0.04301,
    "previousClose":  null,
    "volume":  null,
    "baseVolume":  480.600000000000022737,
    "quoteVolume":  20.670605999999999369,
    "bidVolume":  null,
    "askVolume":  null,
    "change":  -0.00084,
    "percentage":  -1.90999999999999992,
    "timestamp":  1767228929588,
    "datetime":  "2026-01-01T00:55:29.588883",
    "exchange_timestamp":  "2026-01-01T00:55:29.588885",
    "data_source":  "official_exchange_api",
    "exchange_id":  "cex"}]}