{"timeframe":  "24h",
"token":  "kaspa",
"exchange":  "coinex",
"resolution":  "1m",
"count":  35,
"data":  [{"token":  "Kaspa",
    "exchange":  "coinex",
    "symbol":  "KAS/USDT",
    "last":  0.044720000000000003,
    "bid":  null,
    "ask":  null,
    "open":  0.042888999999999997,
    "close":  0.044720000000000003,
    "high":  0.044791999999999998,
    "low":  0.042257999999999997,
    "average":  0.043804000000000003,
    "vwap":  null,
    "previousClose":  null,
    "volume":  null,
    "baseVolume":  1336053.037219489924609661,
    "quoteVolume":  59748.291824455591267906,
    "bidVolume":  391505.982490880007389933,
    "askVolume":  341847.309525820019189268,
    "change":  0.001831,
    "percentage":  4.269159924456154442,
    "timestamp":  1767312009163,
    "datetime":  "2026-01-02T00:00:09.163722",
    "exchange_timestamp":  "2026-01-02T00:00:09.163723",
    "data_source":  "official_exchange_api",
    "exchange_id":  "coinex"},
  {"token":  "Kaspa",
    "exchange":  "coinex",
    "symbol":  "KAS/USDT",
    "last":  0.044720000000000003,
    "bid":  null,
    "ask":  null,
    "open":  0.042888000000000003,
    "close":  0.044720000000000003,
    "high":  0.044791999999999998,
    "low":  0.042257999999999997,
    "average":  0.043804000000000003,
    "vwap":  null,
    "previousClose":  null,
    "volume":  null,
    "baseVolume":  1335993.537219489924609661,
    "quoteVolume":  59745.630984455594443716,
    "bidVolume":  391505.982490880007389933,
    "askVolume":  341847.309525820019189268,
    "change":  0.001832,
    "percentage":  4.271591121059503671,
    "timestamp":  1767312035947,
    "datetime":  "2026-01-02T00:00:35.947742",
    "exchange_timestamp":  "2026-01-02T00:00:35.947743",
    "data_source":  "official_exchange_api",
    "exchange_id":  "coinex"},
  {"token":  "Kaspa",
    "exchange":  "coinex",
    "symbol":  "KAS/USDT",
    "last":  0.044729999999999999,
    "bid":  null,
    "ask":  null,
    "open":  0.042923000000000003,
    "close":  0.044729999999999999,
    "high":  0.044791999999999998,
    "low":  0.042257999999999997,
    "average":  0.043825999999999997,
    "vwap":  null,
    "previousClose":  null,
    "volume":  null,
    "baseVolume":  1335993.037219489924609661,
    "quoteVolume":  59758.968554827784828376,
    "bidVolume":  391506.982490880007389933,
    "askVolume":  341847.309525820019189268,
    "change":  0.001807,
    "percentage":  4.209864175383827067,
    "timestamp":  1767312082376,
    "datetime":  "2026-01-02T00:01:22.376477",
    "exchange_timestamp":  "2026-01-02T00:01:22.376478",
    "data_source":  "official_exchange_api",
    "exchange_id":  "coinex"},
  {"token":  "Kaspa",
    "exchange":  "coinex",
    "symbol":  "KAS/USDT",
    "last":  0.044729999999999999,
    "bid":  null,
    "ask":  null,
    "open":  0.042923000000000003,
    "close":  0.044729999999999999,
    "high":  0.044791999999999998,
    "low":  0.042257999999999997,
    "average":  0.043825999999999997,
    "vwap":  null,
    "previousClose":  null,
    "volume":  null,
    "baseVolume":  1335993.037219489924609661,
    "quoteVolume":  59758.968554827784828376,
    "bidVolume":  391506.982490880007389933,
    "askVolume":  341847.309525820019189268,
    "change":  0.001807,
    "percentage":  4.209864175383827067,
    "timestamp":  1767312084720,
    "datetime":  "2026-01-02T00:01:24.720207",
    "exchange_timestamp":  "2026-01-02T00:01:24.720208",
    "data_source":  "official_exchange_api",
    "exchange_id":  "coinex"},
  {"token":  "Kaspa",
    "exchange":  "coinex",
    "symbol":  "KAS/USDT",
    "last":  0.044729999999999999,
    "bid":  null,
    "ask":  null,
    "open":  0.042923000000000003,
    "close":  0.044729999999999999,
    "high":  0.044791999999999998,
    "low":  0.042257999999999997,
    "average":  0.043825999999999997,
    "vwap":  null,
    "previousClose":  null,
    "volume":  null,
    "baseVolume":  1336049.537219489924609661,
    "quoteVolume":  59761.49579982778232079,
    "bidVolume":  391506.982490880007389933,
    "askVolume":  341845.809525820019189268,
    "change":  0.001807,
    "percentage":  4.209864175383827067,
    "timestamp":  1767312132871,
    "datetime":  "2026-01-02T00:02:12.871728",
    "exchange_timestamp":  "2026-01-02T00:02:12.871729",
    "data_source":  "official_exchange_api",
    "exchange_id":  "coinex"},
  {"token":  "Kaspa",
    "exchange":  "coinex",
    "symbol":  "KAS/USDT",
    "last":  0.044729999999999999,
    "bid":  null,
    "ask":  null,
    "open":  0.042928000000000001,
    "close":  0.044729999999999999,
    "high":  0.044791999999999998,
    "low":  0.042257999999999997,
    "average":  0.043829,
    "vwap":  null,
    "previousClose":  null,
    "volume":  null,
    "baseVolume":  1335990.037219489924609661,
    "quoteVolume":  59758.834364827780518681,
    "bidVolume":  391506.982490880007389933,
    "askVolume":  341845.809525820019189268,
    "change":  0.001802,
    "percentage":  4.197726425642937187,
    "timestamp":  1767312156485,
    "datetime":  "2026-01-02T00:02:36.485071",
    "exchange_timestamp":  "2026-01-02T00:02:36.485072",
    "data_source":  "official_exchange_api",
    "exchange_id":  "coinex"},
  {"token":  "Kaspa",
    "exchange":  "coinex",
    "symbol":  "KAS/USDT",
    "last":  0.044724,
    "bid":  null,
    "ask":  null,
    "open":  0.042928000000000001,
    "close":  0.044724,
    "high":  0.044791999999999998,
    "low":  0.042257999999999997,
    "average":  0.043825999999999997,
    "vwap":  null,
    "previousClose":  null,
    "volume":  null,
    "baseVolume":  1336047.537219489924609661,
    "quoteVolume":  59753.390054604467877652,
    "bidVolume":  391506.982490880007389933,
    "askVolume":  341847.309525820019189268,
    "change":  0.001796,
    "percentage":  4.183749534103615275,
    "timestamp":  1767312181275,
    "datetime":  "2026-01-02T00:03:01.275053",
    "exchange_timestamp":  "2026-01-02T00:03:01.275054",
    "data_source":  "official_exchange_api",
    "exchange_id":  "coinex"},
  {"token":  "Kaspa",
    "exchange":  "coinex",
    "symbol":  "KAS/USDT",
    "last":  0.044715999999999999,
    "bid":  null,
    "ask":  null,
    "open":  0.042928000000000001,
    "close":  0.044715999999999999,
    "high":  0.044791999999999998,
    "low":  0.042257999999999997,
    "average":  0.043822,
    "vwap":  null,
    "previousClose":  null,
    "volume":  null,
    "baseVolume":  1336048.037219489924609661,
    "quoteVolume":  59742.724032306708977558,
    "bidVolume":  391564.982490880007389933,
    "askVolume":  341789.448748440016061068,
    "change":  0.001788,
    "percentage":  4.165113678717853318,
    "timestamp":  1767312232601,
    "datetime":  "2026-01-02T00:03:52.601627",
    "exchange_timestamp":  "2026-01-02T00:03:52.601628",
    "data_source":  "official_exchange_api",
    "exchange_id":  "coinex"},
  {"token":  "Kaspa",
    "exchange":  "coinex",
    "symbol":  "KAS/USDT",
    "last":  0.044715999999999999,
    "bid":  null,
    "ask":  null,
    "open":  0.042928000000000001,
    "close":  0.044715999999999999,
    "high":  0.044791999999999998,
    "low":  0.042257999999999997,
    "average":  0.043822,
    "vwap":  null,
    "previousClose":  null,
    "volume":  null,
    "baseVolume":  1336048.037219489924609661,
    "quoteVolume":  59742.724032306708977558,
    "bidVolume":  391564.982490880007389933,
    "askVolume":  341789.448748440016061068,
    "change":  0.001788,
    "percentage":  4.165113678717853318,
    "timestamp":  1767312232897,
    "datetime":  "2026-01-02T00:03:52.897638",
    "exchange_timestamp":  "2026-01-02T00:03:52.897639",
    "data_source":  "official_exchange_api",
    "exchange_id":  "coinex"},
  {"token":  "Kaspa",
    "exchange":  "coinex",
    "symbol":  "KAS/USDT",
    "last":  0.044720999999999997,
    "bid":  null,
    "ask":  null,
    "open":  0.042928000000000001,
    "close":  0.044720999999999997,
    "high":  0.044791999999999998,
    "low":  0.042257999999999997,
    "average":  0.043824000000000002,
    "vwap":  null,
    "previousClose":  null,
    "volume":  null,
    "baseVolume":  1336046.537219489924609661,
    "quoteVolume":  59749.337190992802788969,
    "bidVolume":  391564.982490880007389933,
    "askVolume":  341788.948748440016061068,
    "change":  0.001793,
    "percentage":  4.176761088333954319,
    "timestamp":  1767312282425,
    "datetime":  "2026-01-02T00:04:42.425774",
    "exchange_timestamp":  "2026-01-02T00:04:42.425776",
    "data_source":  "official_exchange_api",
    "exchange_id":  "coinex"},
  {"token":  "Kaspa",
    "exchange":  "coinex",
    "symbol":  "KAS/USDT",
    "last":  0.044616999999999997,
    "bid":  null,
    "ask":  null,
    "open":  0.042929000000000002,
    "close":  0.044616999999999997,
    "high":  0.044791999999999998,
    "low":  0.042257999999999997,
    "average":  0.043772999999999999,
    "vwap":  null,
    "previousClose":  null,
    "volume":  null,
    "baseVolume":  1342608.809014159953221679,
    "quoteVolume":  59903.177231784771720413,
    "bidVolume":  391505.982490880007389933,
    "askVolume":  345659.948374609986785799,
    "change":  0.001688,
    "percentage":  3.932073889445363069,
    "timestamp":  1767312347537,
    "datetime":  "2026-01-02T00:05:47.537965",
    "exchange_timestamp":  "2026-01-02T00:05:47.537966",
    "data_source":  "official_exchange_api",
    "exchange_id":  "coinex"},
  {"token":  "Kaspa",
    "exchange":  "coinex",
    "symbol":  "KAS/USDT",
    "last":  0.044526999999999997,
    "bid":  null,
    "ask":  null,
    "open":  0.042928000000000001,
    "close":  0.044526999999999997,
    "high":  0.044791999999999998,
    "low":  0.042257999999999997,
    "average":  0.043727000000000002,
    "vwap":  null,
    "previousClose":  null,
    "volume":  null,
    "baseVolume":  1347251.07647276995703578,
    "quoteVolume":  59989.04868210302083753,
    "bidVolume":  391505.982490880007389933,
    "askVolume":  340942.188308499986305833,
    "change":  0.001599,
    "percentage":  3.724841595229221092,
    "timestamp":  1767312401190,
    "datetime":  "2026-01-02T00:06:41.190808",
    "exchange_timestamp":  "2026-01-02T00:06:41.190810",
    "data_source":  "official_exchange_api",
    "exchange_id":  "coinex"},
  {"token":  "Kaspa",
    "exchange":  "coinex",
    "symbol":  "KAS/USDT",
    "last":  0.044526999999999997,
    "bid":  null,
    "ask":  null,
    "open":  0.042928000000000001,
    "close":  0.044526999999999997,
    "high":  0.044791999999999998,
    "low":  0.042257999999999997,
    "average":  0.043727000000000002,
    "vwap":  null,
    "previousClose":  null,
    "volume":  null,
    "baseVolume":  1347251.07647276995703578,
    "quoteVolume":  59989.04868210302083753,
    "bidVolume":  391505.982490880007389933,
    "askVolume":  340942.188308499986305833,
    "change":  0.001599,
    "percentage":  3.724841595229221092,
    "timestamp":  1767312408622,
    "datetime":  "2026-01-02T00:06:48.622895",
    "exchange_timestamp":  "2026-01-02T00:06:48.622896",
    "data_source":  "official_exchange_api",
    "exchange_id":  "coinex"},
  {"token":  "Kaspa",
    "exchange":  "coinex",
    "symbol":  "KAS/USDT",
    "last":  0.044528999999999999,
    "bid":  null,
    "ask":  null,
    "open":  0.042928000000000001,
    "close":  0.044528999999999999,
    "high":  0.044791999999999998,
    "low":  0.042257999999999997,
    "average":  0.043728000000000003,
    "vwap":  null,
    "previousClose":  null,
    "volume":  null,
    "baseVolume":  1377333.016394899925217032,
    "quoteVolume":  61331.261887048494827468,
    "bidVolume":  391395.482490880007389933,
    "askVolume":  371095.735839319997467101,
    "change":  0.001601,
    "percentage":  3.729500559075661581,
    "timestamp":  1767312461777,
    "datetime":  "2026-01-02T00:07:41.777948",
    "exchange_timestamp":  "2026-01-02T00:07:41.777950",
    "data_source":  "official_exchange_api",
    "exchange_id":  "coinex"},
  {"token":  "Kaspa",
    "exchange":  "coinex",
    "symbol":  "KAS/USDT",
    "last":  0.044528999999999999,
    "bid":  null,
    "ask":  null,
    "open":  0.042929000000000002,
    "close":  0.044528999999999999,
    "high":  0.044791999999999998,
    "low":  0.042257999999999997,
    "average":  0.043728999999999997,
    "vwap":  null,
    "previousClose":  null,
    "volume":  null,
    "baseVolume":  1377220.024620010051876307,
    "quoteVolume":  61326.230476304423063993,
    "bidVolume":  391395.482490880007389933,
    "askVolume":  371095.735839319997467101,
    "change":  0.0016,
    "percentage":  3.727084255398448676,
    "timestamp":  1767312484350,
    "datetime":  "2026-01-02T00:08:04.350345",
    "exchange_timestamp":  "2026-01-02T00:08:04.350346",
    "data_source":  "official_exchange_api",
    "exchange_id":  "coinex"},
  {"token":  "Kaspa",
    "exchange":  "coinex",
    "symbol":  "KAS/USDT",
    "last":  0.044532000000000002,
    "bid":  null,
    "ask":  null,
    "open":  0.042929000000000002,
    "close":  0.044532000000000002,
    "high":  0.044791999999999998,
    "low":  0.042257999999999997,
    "average":  0.043729999999999998,
    "vwap":  null,
    "previousClose":  null,
    "volume":  null,
    "baseVolume":  1377275.024620010051876307,
    "quoteVolume":  61332.81139637828891864,
    "bidVolume":  391450.482490880007389933,
    "askVolume":  371039.735839319997467101,
    "change":  0.001603,
    "percentage":  3.734072538377320782,
    "timestamp":  1767312523376,
    "datetime":  "2026-01-02T00:08:43.376281",
    "exchange_timestamp":  "2026-01-02T00:08:43.376283",
    "data_source":  "official_exchange_api",
    "exchange_id":  "coinex"},
  {"token":  "Kaspa",
    "exchange":  "coinex",
    "symbol":  "KAS/USDT",
    "last":  0.044532000000000002,
    "bid":  null,
    "ask":  null,
    "open":  0.042929000000000002,
    "close":  0.044532000000000002,
    "high":  0.044791999999999998,
    "low":  0.042257999999999997,
    "average":  0.043729999999999998,
    "vwap":  null,
    "previousClose":  null,
    "volume":  null,
    "baseVolume":  1377217.524620010051876307,
    "quoteVolume":  61330.250806378287961707,
    "bidVolume":  391450.482490880007389933,
    "askVolume":  371039.735839319997467101,
    "change":  0.001603,
    "percentage":  3.734072538377320782,
    "timestamp":  1767312558175,
    "datetime":  "2026-01-02T00:09:18.175643",
    "exchange_timestamp":  "2026-01-02T00:09:18.175644",
    "data_source":  "official_exchange_api",
    "exchange_id":  "coinex"},
  {"token":  "Kaspa",
    "exchange":  "coinex",
    "symbol":  "KAS/USDT",
    "last":  0.044532000000000002,
    "bid":  null,
    "ask":  null,
    "open":  0.042929000000000002,
    "close":  0.044532000000000002,
    "high":  0.044791999999999998,
    "low":  0.042257999999999997,
    "average":  0.043729999999999998,
    "vwap":  null,
    "previousClose":  null,
    "volume":  null,
    "baseVolume":  1377217.524620010051876307,
    "quoteVolume":  61330.250806378287961707,
    "bidVolume":  391450.482490880007389933,
    "askVolume":  371039.735839319997467101,
    "change":  0.001603,
    "percentage":  3.734072538377320782,
    "timestamp":  1767312571288,
    "datetime":  "2026-01-02T00:09:31.288756",
    "exchange_timestamp":  "2026-01-02T00:09:31.288757",
    "data_source":  "official_exchange_api",
    "exchange_id":  "coinex"},
  {"token":  "Kaspa",
    "exchange":  "coinex",
    "symbol":  "KAS/USDT",
    "last":  0.044547999999999997,
    "bid":  null,
    "ask":  null,
    "open":  0.042928000000000001,
    "close":  0.044547999999999997,
    "high":  0.044791999999999998,
    "low":  0.042257999999999997,
    "average":  0.043737999999999999,
    "vwap":  null,
    "previousClose":  null,
    "volume":  null,
    "baseVolume":  1377217.524620010051876307,
    "quoteVolume":  61352.286286772206949536,
    "bidVolume":  391452.482490880007389933,
    "askVolume":  371039.735839319997467101,
    "change":  0.00162,
    "percentage":  3.773760715616846895,
    "timestamp":  1767312625849,
    "datetime":  "2026-01-02T00:10:25.849562",
    "exchange_timestamp":  "2026-01-02T00:10:25.849564",
    "data_source":  "official_exchange_api",
    "exchange_id":  "coinex"},
  {"token":  "Kaspa",
    "exchange":  "coinex",
    "symbol":  "KAS/USDT",
    "last":  0.044547999999999997,
    "bid":  null,
    "ask":  null,
    "open":  0.042928000000000001,
    "close":  0.044547999999999997,
    "high":  0.044791999999999998,
    "low":  0.042257999999999997,
    "average":  0.043737999999999999,
    "vwap":  null,
    "previousClose":  null,
    "volume":  null,
    "baseVolume":  1377217.524620010051876307,
    "quoteVolume":  61352.286286772206949536,
    "bidVolume":  391452.482490880007389933,
    "askVolume":  371039.735839319997467101,
    "change":  0.00162,
    "percentage":  3.773760715616846895,
    "timestamp":  1767312634856,
    "datetime":  "2026-01-02T00:10:34.856493",
    "exchange_timestamp":  "2026-01-02T00:10:34.856495",
    "data_source":  "official_exchange_api",
    "exchange_id":  "coinex"},
  {"token":  "Kaspa",
    "exchange":  "coinex",
    "symbol":  "KAS/USDT",
    "last":  0.044537,
    "bid":  null,
    "ask":  null,
    "open":  0.042928000000000001,
    "close":  0.044537,
    "high":  0.044791999999999998,
    "low":  0.042257999999999997,
    "average":  0.043732,
    "vwap":  null,
    "previousClose":  null,
    "volume":  null,
    "baseVolume":  1377277.024620010051876307,
    "quoteVolume":  61339.786845501388597768,
    "bidVolume":  391511.982490880007389933,
    "askVolume":  370983.735839319997467101,
    "change":  0.001609,
    "percentage":  3.748136414461423538,
    "timestamp":  1767312670622,
    "datetime":  "2026-01-02T00:11:10.622196",
    "exchange_timestamp":  "2026-01-02T00:11:10.622198",
    "data_source":  "official_exchange_api",
    "exchange_id":  "coinex"},
  {"token":  "Kaspa",
    "exchange":  "coinex",
    "symbol":  "KAS/USDT",
    "last":  0.044538000000000001,
    "bid":  null,
    "ask":  null,
    "open":  0.042928000000000001,
    "close":  0.044538000000000001,
    "high":  0.044791999999999998,
    "low":  0.042257999999999997,
    "average":  0.043733000000000001,
    "vwap":  null,
    "previousClose":  null,
    "volume":  null,
    "baseVolume":  1377281.024620010051876307,
    "quoteVolume":  61341.342274526010442059,
    "bidVolume":  391511.982490880007389933,
    "askVolume":  370983.235839319997467101,
    "change":  0.00161,
    "percentage":  3.750465896384644005,
    "timestamp":  1767312716235,
    "datetime":  "2026-01-02T00:11:56.235350",
    "exchange_timestamp":  "2026-01-02T00:11:56.235351",
    "data_source":  "official_exchange_api",
    "exchange_id":  "coinex"},
  {"token":  "Kaspa",
    "exchange":  "coinex",
    "symbol":  "KAS/USDT",
    "last":  0.044538000000000001,
    "bid":  null,
    "ask":  null,
    "open":  0.042928000000000001,
    "close":  0.044538000000000001,
    "high":  0.044791999999999998,
    "low":  0.042257999999999997,
    "average":  0.043733000000000001,
    "vwap":  null,
    "previousClose":  null,
    "volume":  null,
    "baseVolume":  1377281.024620010051876307,
    "quoteVolume":  61341.342274526010442059,
    "bidVolume":  391511.982490880007389933,
    "askVolume":  370983.235839319997467101,
    "change":  0.00161,
    "percentage":  3.750465896384644005,
    "timestamp":  1767312730584,
    "datetime":  "2026-01-02T00:12:10.584409",
    "exchange_timestamp":  "2026-01-02T00:12:10.584410",
    "data_source":  "official_exchange_api",
    "exchange_id":  "coinex"},
  {"token":  "Kaspa",
    "exchange":  "coinex",
    "symbol":  "KAS/USDT",
    "last":  0.044544,
    "bid":  null,
    "ask":  null,
    "open":  0.042929000000000002,
    "close":  0.044544,
    "high":  0.044791999999999998,
    "low":  0.042257999999999997,
    "average":  0.043735999999999997,
    "vwap":  null,
    "previousClose":  null,
    "volume":  null,
    "baseVolume":  1377280.524620010051876307,
    "quoteVolume":  61349.583688673730648588,
    "bidVolume":  391509.982490880007389933,
    "askVolume":  370983.235839319997467101,
    "change":  0.001615,
    "percentage":  3.76202567029280921,
    "timestamp":  1767312779202,
    "datetime":  "2026-01-02T00:12:59.202963",
    "exchange_timestamp":  "2026-01-02T00:12:59.202964",
    "data_source":  "official_exchange_api",
    "exchange_id":  "coinex"},
  {"token":  "Kaspa",
    "exchange":  "coinex",
    "symbol":  "KAS/USDT",
    "last":  0.044544,
    "bid":  null,
    "ask":  null,
    "open":  0.042929000000000002,
    "close":  0.044544,
    "high":  0.044791999999999998,
    "low":  0.042257999999999997,
    "average":  0.043735999999999997,
    "vwap":  null,
    "previousClose":  null,
    "volume":  null,
    "baseVolume":  1377280.524620010051876307,
    "quoteVolume":  61349.583688673730648588,
    "bidVolume":  391509.982490880007389933,
    "askVolume":  370983.235839319997467101,
    "change":  0.001615,
    "percentage":  3.76202567029280921,
    "timestamp":  1767312789301,
    "datetime":  "2026-01-02T00:13:09.301246",
    "exchange_timestamp":  "2026-01-02T00:13:09.301248",
    "data_source":  "official_exchange_api",
    "exchange_id":  "coinex"},
  {"token":  "Kaspa",
    "exchange":  "coinex",
    "symbol":  "KAS/USDT",
    "last":  0.044532000000000002,
    "bid":  null,
    "ask":  null,
    "open":  0.042928000000000001,
    "close":  0.044532000000000002,
    "high":  0.044791999999999998,
    "low":  0.042257999999999997,
    "average":  0.043729999999999998,
    "vwap":  null,
    "previousClose":  null,
    "volume":  null,
    "baseVolume":  1377281.024620010051876307,
    "quoteVolume":  61333.078588378288259264,
    "bidVolume":  391566.982490880007389933,
    "askVolume":  370930.93901932000881061,
    "change":  0.001604,
    "percentage":  3.736489004845322537,
    "timestamp":  1767312828882,
    "datetime":  "2026-01-02T00:13:48.882714",
    "exchange_timestamp":  "2026-01-02T00:13:48.882715",
    "data_source":  "official_exchange_api",
    "exchange_id":  "coinex"},
  {"token":  "Kaspa",
    "exchange":  "coinex",
    "symbol":  "KAS/USDT",
    "last":  0.044532000000000002,
    "bid":  null,
    "ask":  null,
    "open":  0.042929000000000002,
    "close":  0.044532000000000002,
    "high":  0.044791999999999998,
    "low":  0.042257999999999997,
    "average":  0.043729999999999998,
    "vwap":  null,
    "previousClose":  null,
    "volume":  null,
    "baseVolume":  1377221.524620010051876307,
    "quoteVolume":  61330.428934378287522122,
    "bidVolume":  391566.982490880007389933,
    "askVolume":  370930.93901932000881061,
    "change":  0.001603,
    "percentage":  3.734072538377320782,
    "timestamp":  1767312866205,
    "datetime":  "2026-01-02T00:14:26.205120",
    "exchange_timestamp":  "2026-01-02T00:14:26.205121",
    "data_source":  "official_exchange_api",
    "exchange_id":  "coinex"},
  {"token":  "Kaspa",
    "exchange":  "coinex",
    "symbol":  "KAS/USDT",
    "last":  0.044534999999999998,
    "bid":  null,
    "ask":  null,
    "open":  0.042929000000000002,
    "close":  0.044534999999999998,
    "high":  0.044791999999999998,
    "low":  0.042257999999999997,
    "average":  0.043732,
    "vwap":  null,
    "previousClose":  null,
    "volume":  null,
    "baseVolume":  1377281.024620010051876307,
    "quoteVolume":  61337.210431452142074704,
    "bidVolume":  391514.148782760021276772,
    "askVolume":  370990.43901932000881061,
    "change":  0.001606,
    "percentage":  3.741060821356192889,
    "timestamp":  1767312882680,
    "datetime":  "2026-01-02T00:14:42.680557",
    "exchange_timestamp":  "2026-01-02T00:14:42.680558",
    "data_source":  "official_exchange_api",
    "exchange_id":  "coinex"},
  {"token":  "Kaspa",
    "exchange":  "coinex",
    "symbol":  "KAS/USDT",
    "last":  0.044534999999999998,
    "bid":  null,
    "ask":  null,
    "open":  0.042929000000000002,
    "close":  0.044534999999999998,
    "high":  0.044791999999999998,
    "low":  0.042257999999999997,
    "average":  0.043732,
    "vwap":  null,
    "previousClose":  null,
    "volume":  null,
    "baseVolume":  1377224.024620010051876307,
    "quoteVolume":  61334.671936452148656826,
    "bidVolume":  391514.148782760021276772,
    "askVolume":  370990.43901932000881061,
    "change":  0.001606,
    "percentage":  3.741060821356192889,
    "timestamp":  1767312931002,
    "datetime":  "2026-01-02T00:15:31.002439",
    "exchange_timestamp":  "2026-01-02T00:15:31.002440",
    "data_source":  "official_exchange_api",
    "exchange_id":  "coinex"},
  {"token":  "Kaspa",
    "exchange":  "coinex",
    "symbol":  "KAS/USDT",
    "last":  0.044528999999999999,
    "bid":  null,
    "ask":  null,
    "open":  0.042929000000000002,
    "close":  0.044528999999999999,
    "high":  0.044791999999999998,
    "low":  0.042257999999999997,
    "average":  0.043728999999999997,
    "vwap":  null,
    "previousClose":  null,
    "volume":  null,
    "baseVolume":  1377279.024620010051876307,
    "quoteVolume":  61328.857687304429418873,
    "bidVolume":  391458.138932340021710843,
    "askVolume":  371045.43901932000881061,
    "change":  0.0016,
    "percentage":  3.727084255398448676,
    "timestamp":  1767312940937,
    "datetime":  "2026-01-02T00:15:40.937789",
    "exchange_timestamp":  "2026-01-02T00:15:40.937791",
    "data_source":  "official_exchange_api",
    "exchange_id":  "coinex"},
  {"token":  "Kaspa",
    "exchange":  "coinex",
    "symbol":  "KAS/USDT",
    "last":  0.044528999999999999,
    "bid":  null,
    "ask":  null,
    "open":  0.042946999999999999,
    "close":  0.044528999999999999,
    "high":  0.044791999999999998,
    "low":  0.042257999999999997,
    "average":  0.043737999999999999,
    "vwap":  null,
    "previousClose":  null,
    "volume":  null,
    "baseVolume":  1373940.597786630038172007,
    "quoteVolume":  61180.200878840849327389,
    "bidVolume":  391458.138932340021710843,
    "askVolume":  371045.43901932000881061,
    "change":  0.001582,
    "percentage":  3.683610030968402782,
    "timestamp":  1767312982170,
    "datetime":  "2026-01-02T00:16:22.170004",
    "exchange_timestamp":  "2026-01-02T00:16:22.170005",
    "data_source":  "official_exchange_api",
    "exchange_id":  "coinex"},
  {"token":  "Kaspa",
    "exchange":  "coinex",
    "symbol":  "KAS/USDT",
    "last":  0.044528999999999999,
    "bid":  null,
    "ask":  null,
    "open":  0.042946999999999999,
    "close":  0.044528999999999999,
    "high":  0.044791999999999998,
    "low":  0.042257999999999997,
    "average":  0.043737999999999999,
    "vwap":  null,
    "previousClose":  null,
    "volume":  null,
    "baseVolume":  1373995.597786630038172007,
    "quoteVolume":  61182.649973840845632367,
    "bidVolume":  391454.638932340021710843,
    "askVolume":  371045.43901932000881061,
    "change":  0.001582,
    "percentage":  3.683610030968402782,
    "timestamp":  1767313021418,
    "datetime":  "2026-01-02T00:17:01.418240",
    "exchange_timestamp":  "2026-01-02T00:17:01.418241",
    "data_source":  "official_exchange_api",
    "exchange_id":  "coinex"},
  {"token":  "Kaspa",
    "exchange":  "coinex",
    "symbol":  "KAS/USDT",
    "last":  0.044528999999999999,
    "bid":  null,
    "ask":  null,
    "open":  0.042946999999999999,
    "close":  0.044528999999999999,
    "high":  0.044791999999999998,
    "low":  0.042257999999999997,
    "average":  0.043737999999999999,
    "vwap":  null,
    "previousClose":  null,
    "volume":  null,
    "baseVolume":  1373995.597786630038172007,
    "quoteVolume":  61182.649973840845632367,
    "bidVolume":  391454.638932340021710843,
    "askVolume":  371045.43901932000881061,
    "change":  0.001582,
    "percentage":  3.683610030968402782,
    "timestamp":  1767313033950,
    "datetime":  "2026-01-02T00:17:13.950186",
    "exchange_timestamp":  "2026-01-02T00:17:13.950187",
    "data_source":  "official_exchange_api",
    "exchange_id":  "coinex"},
  {"token":  "Kaspa",
    "exchange":  "coinex",
    "symbol":  "KAS/USDT",
    "last":  0.044527999999999998,
    "bid":  null,
    "ask":  null,
    "open":  0.042946999999999999,
    "close":  0.044527999999999998,
    "high":  0.044791999999999998,
    "low":  0.042257999999999997,
    "average":  0.043736999999999998,
    "vwap":  null,
    "previousClose":  null,
    "volume":  null,
    "baseVolume":  1373996.097786630038172007,
    "quoteVolume":  61181.29824224305775715,
    "bidVolume":  391514.138932340021710843,
    "askVolume":  370986.93901932000881061,
    "change":  0.001581,
    "percentage":  3.681281579621393796,
    "timestamp":  1767313079770,
    "datetime":  "2026-01-02T00:17:59.770357",
    "exchange_timestamp":  "2026-01-02T00:17:59.770357",
    "data_source":  "official_exchange_api",
    "exchange_id":  "coinex"},
  {"token":  "Kaspa",
    "exchange":  "coinex",
    "symbol":  "KAS/USDT",
    "last":  0.044527999999999998,
    "bid":  null,
    "ask":  null,
    "open":  0.042946999999999999,
    "close":  0.044527999999999998,
    "high":  0.044791999999999998,
    "low":  0.042257999999999997,
    "average":  0.043736999999999998,
    "vwap":  null,
    "previousClose":  null,
    "volume":  null,
    "baseVolume":  1373936.597786630038172007,
    "quoteVolume":  61178.648826243057555985,
    "bidVolume":  391514.138932340021710843,
    "askVolume":  370986.93901932000881061,
    "change":  0.001581,
    "percentage":  3.681281579621393796,
    "timestamp":  1767313102936,
    "datetime":  "2026-01-02T00:18:22.936676",
    "exchange_timestamp":  "2026-01-02T00:18:22.936678",
    "data_source":  "official_exchange_api",
    "exchange_id":  "coinex"}]}